Workbook
Name \0: [1]K!$D$1
Name \B: '[1]PRODUCT COST SHEET - PRIMA'!$B$86
Name \C: [1]SPLITLCP!$BA$1:$BA$3
Name \L: '[1]SS PRIMA PLUS'!$B$109
Name \M: '[1]SS PRIMA HC'!$B$110
Name \P: '[1]PRODUCT & CATEGORY PROFITABILIT'!$B$72
Name \S: [1]K!$E$10
Name \T: [1]K!$K$11
Name \X: '[1]PRODUCT & CATEGORY PROFITABILIT'!$B$74:$B$83
Name \Z: '[1]SS PRIMA UNI'!$B$114
Name _DCC4: [1]DISH!$D$29:$Q$29
Name _dd1: #REF!
Name _dd2: #REF!
Name _DSH1: [1]DISH!$D$11:$Q$14
Name _FCC1: [1]FCC!$D$11:$R$15
Name _FCC3: [1]FCC!$D$25:$R$25
Name _HSC1: [1]HSC!$D$11:$Q$11
Name _HSC4: [1]HSC!$D$29:$R$29
Name _LCP1: [1]SPLITLCP!$C$6:$P$13
Name _LCP2: [1]SPLITLCP!$C$24:$P$31
Name _LCP3: [1]SPLITLCP!$C$43:$P$50
Name _MLT3: [1]NBD!$D$24:$Q$24
Name _MLT4: [1]NBD!$D$31:$Q$31
Name _MLT5: [1]NBD!$D$35:$Q$35
Name _MLT7: [1]NBD!$D$48:$Q$48
Name _NBD1: [1]NBD!$D$11:$R$11
Name _RM426: '[1]SUMMARY REPORTS'!#REF!
Name a: #REF!
Name AA: [1]LCPSECT!$R$17:$R$27
Name aaa: #REF!
Name AB: #REF!
Name AII: #REF!
Name aile: [1]BLENDAX!#REF!
Name APAPCY: #REF!
Name APAPCY_1: #REF!
Name APAPCY_2: #REF!
Name APBYND: #REF!
Name APPREV: #REF!
Name APUNAPCY: #REF!
Name APUNAPCY_1: #REF!
Name APUNAPCY_2: #REF!
Name as: #REF!
Name asdf: #REF!
Name BA_1: '[1]Sched 8'!#REF!
Name BA_2: '[1]Sched 8'!#REF!
Name BA_3: '[1]Sched 8'!#REF!
Name BA_4: '[1]Sched 8'!#REF!
Name BA_5: '[1]Sched 8'!#REF!
Name BA_6: '[1]Sched 8'!#REF!
Name Baby: #REF!
Name baby1: #REF!
Name BB: [1]LCPSECT!$R$17:$R$27
Name bbb: '[1]Sched 8'!#REF!
Name Bev: #REF!
Name BOM_maintained: #REF!
Name Border11: #REF!
Name Border12: #REF!
Name Border13: #REF!
Name Border14: #REF!
Name Border15: #REF!

Sheet CPS
A1: Task | B1: Owner | C1: Time
A2: Health check kick off/Communication email shared | B2: Suz. | C2: 5/11
A3: Finish Health check questions & assessment | B3: Plant/ESS SNP leaders, PSC Owners | C3: 5/11-5/20
A4: Clarification with Plant/PSC owners | B4: Suz./Plant/ESS SNP leaders, PSC owners | C4: 5/21-5/26
A5: Health check result peer reviewed/calibrated and action plan aligned | B5: Suz. /Grace/Zhang Sen | C5: 5/29
A6: Review with Lawrence/Approval in system | B6: Suz./Grace/Lawrence | C6: 6/25
A7: Critical Actions closed | B7: Suz. | C7: 9/30
A8: Major Actions closed | B8: Suz. | C8: 12/30

Sheet 2Y # of  Qs compare
A2: # of Questions Compare
B3: Results | D3: Capability | F3: Processes | H3: Systems | J3: Total
A4: Work Process Assessment | B4: FY2526 | C4: FY2425 | D4: FY2526 | E4: FY2425 | F4: FY2526 | G4: FY2425 | H4: FY2526 | I4: FY2425 | J4: FY2526 | K4: FY2425
A5: Integrated Inventory Management | B5: 2 | C5: 3 | D5: 5 | E5: 6 | F5: 21 | G5: 21 | H5: 8 | I5: 8 | J5: =SUM(B5,D5,F5,H5) -> 36 | K5: =SUM(C5,E5,G5,I5) -> 38
A6: Integrated Service | B6: 1 | C6: 1 | D6: 4 | E6: 4 | F6: 6 | G6: 6 | H6: 1 | I6: 1 | J6: =SUM(B6,D6,F6,H6) -> 12 | K6: =SUM(C6,E6,G6,I6) -> 12
A7: Production Capacity | B7: 2 | C7: 2 | D7: 3 | E7: 3 | F7: 8 | G7: 8 | H7: 2 | I7: 2 | J7: =SUM(B7,D7,F7,H7) -> 15 | K7: =SUM(C7,E7,G7,I7) -> 15
A8: Supply Chain Orchestration | B8: 2 | C8: 2 | D8: 10 | E8: 10 | F8: 31 | G8: 37 | H8: 4 | I8: 4 | J8: =SUM(B8,D8,F8,H8) -> 47 | K8: =SUM(C8,E8,G8,I8) -> 53
B9: =SUM(B5:B8) -> 7 | C9: =SUM(C5:C8) -> 8 | D9: =SUM(D5:D8) -> 22 | E9: =SUM(E5:E8) -> 23 | F9: =SUM(F5:F8) -> 66 | G9: =SUM(G5:G8) -> 72 | H9: =SUM(H5:H8) -> 15 | I9: =SUM(I5:I8) -> 15 | J9: =SUM(B9,D9,F9,H9) -> 110 | K9: =SUM(C9,E9,G9,I9) -> 118
A11: Highlights changes: | B11: 1. Integrated Inv. management, 3 QS reduced, 1 is from result- situational safety tracking cancelled. 2 Qs. cancelled from process- NPI physically exceed 180 days, UPI discussed in D12. QS NPI qs. >90 evaluation and execution being reviewd and quarterly accural qs. split to 2 qs.
B12: 2. Supply chain Orchestration- Cancel 1 QS- POSS, 2 QS-PCL, 2 QS-POW, 1 QS- MSAnT . MSAnT name changes to Manufacturing agility workshop.
A15: FY2425 Result

Sheet FY2526 Questions & Owners-All 
A1: QS | B1: Work Process | C1: No. | D1: Section | E1: Question | F1: Owner | G1: Rational for Scoring | I1: Score | K1: Criteria for Score 0 | L1: Criteria for Score 1 | M1: Criteria for Score 2 | N1: Question can be marked n/a ? | O1: Additional / Reference links | Q1: Action Plan (Mandatory if Score = 0, 1) | R1: Action Criticality (Critical / non-Critical)
A2: 1 | B2: Integrated Inventory Management | C2: 1 | D2: Results | E2: IM- UPI: Total (FP + RPI) % UPI FYTD and Glide path (remainder of the FY) is on or below BU target for the current FY | F2: PSC-Sophia | I2: 0 | K2: No Glidepaths identified and FYTD UPI off track | L2: FYTD UPI off track but glidepath is set to be on track by FY end | M2: UPI Glidepaths set and FYTD UPI on track | N2: FALSE
A3: 2 | B3: Integrated Inventory Management | C3: 2 | D3: Results | E3: IM: Is the evaluation for NPI is performed within 90 days of NPI is identified? Is the action plan for disposal or depletion of NPI physically executed within 90 days after evaluated? | F3: PSC-Yuchen | I3: 0 | K3: NPI is not evaluated fully within 90 days & NPI is not disposed fully within 90 days after evaluation across the RBU. | L3: NPI evaluated fully within 90 Days or NPI disposed fully within 90 days after evaluation across the RBU. | M3: NPI is evaluated fully within 90 days and NPI is disposed fully within 90 days after evaluation across the RBU (Zero overdue NPI evaluation/disposal) | N3: FALSE
A4: 3 | B4: Integrated Inventory Management | C4: 3 | D4: Capability | E4: ITS – FP: ITS Users are able to run scenarios to investigate impacts of supply chain changes or parameter changes into Safety calculations | F4: PSC-Sophia | I4: 0 | K4: missing capability to use what ifs | L4: BU choices done without using what ifs (even though capability exists) | M4: tool if fully leveraged to run scenarios if needed A-ITS - Is the SNP PE capable of running scenarios with minimal or zero help? - Does the scenario outputs require Operational Strategy updates? IBPI: Manual triggering of IBPI engine to reflect changes of masterdata, active participation in tests improving tool | N4: FALSE
A5: 4 | B5: Integrated Inventory Management | C5: 4 | D5: Capability | E5: ITS – FP& RPM : Are all KU or/and system owners qualified within 6 months from starting role? | F5: PSC-Sophia for FP, Jiawen for RPM | I5: 0 | K5: KU not trained and qualified within 6 months | L5: KU qualified but after 6 months in the role [SUC Targets end users as basic / Key users as Intermediate – CSNP/SNP PE is targeted as a KU] | M5: KU trained and qualified within 6 months in the role A-ITS - Is the SNP PE trained and qualified within first 6 months. IBPI& Prima: IBPI KU trained and qualified within first 6 months [SUC Targets end users as basic / Key users as Intermediate – CSNP/SNP PE is targeted as a KU] | N5: FALSE
A6: 5 | B6: Integrated Inventory Management | C6: 5 | D6: Capability | E6: IM- Leadership: Are the Regional inventory solutions Key Users in place and qualified by Regional BPX via the Step Up Card? | F6: PSC-Sophia | I6: 0 | K6: No IM Key User assigned | L6: Inventory key user assigned but not qualified on IM SUC | M6: Inventory key user assigned and qualified with IM SUC | N6: FALSE
A7: 6 | B7: Integrated Inventory Management | C7: 6 | D7: Capability | E7: Cash RCLA: Is there a Loss Analysis Leader identified for the RBU and is qualified on RCLA Step Up Card ? | F7: PSC-Sophia | I7: 0 | K7: No BU Inventory RBU Leader assigned | L7: RBU Inventory Leader assigned but not qualified on Cash RCLA SUC | M7: RBU Inventory Leader assigned and qualified with Cash RCLA SUC | N7: FALSE
A8: 7 | B8: Integrated Inventory Management | C8: 7 | D8: Capability | E8: Process owner defined for every work process and ensures in process/out process measures are tracked & visible (FP ITS, RPM ITS, Cash RCLA & IM) | F8: PSC-Suz. | I8: 0 | K8: No assigned owner | L8: owner assigned but in process/out process measures not tracked | M8: Owner assigned and in process/out process measures are tracked | N8: FALSE
A9: 8 | B9: Integrated Inventory Management | C9: 8 | D9: Processes | E9: ITS – FP: Was standard PACE model and SWP followed throughout the process? | F9: PSC-Sophia | I9: 0 | K9: process not followed (no review process established, no writeback using standard tool, no owner for BU assigned to work on safety) | L9: some of elements of SWP not applied (like owner not in CSNP team, HPPP manually in planning system, and for IBPI IOPT not incorporated) | M9: All elements working which is proved by results A-ITS P - SNP PE A - SCL C - SCL, IOL, CSP, SIP E - SNP PE, SIP IBPI: weekly process, led by CNA team, Review process done (preferably with dynamic review), end users' business knowledge pulled (preferably inside IBPI, but can be offline), safety on aggregate level in line with glidepath, HPPP done inside IBPI, IOPT linkage opened for 90% of matlocs | N9: FALSE
A10: 9 | B10: Integrated Inventory Management | C10: 9 | D10: Processes | E10: ITS FP: Is master data in ITS tool correct and verified on weekly basis, including parameters coming from ITS operating strategy | F10: PSC-Sophia | I10: 0 | K10: no audit | L10: partial, not regular audit | M10: A-ITS: 99% Overall Masterdata compliance score to ensure mandatory elements including examples: APO Layer 1, Network Completeness, and Centerline Compliance review. IBPI: At least mandatory elements are captured in MD checks: production details, IOPT publishing rate, decision where to store safety + all elements required based on ITS strategy | N10: FALSE
A11: 10 | B11: Integrated Inventory Management | C11: 10 | D11: Processes | E11: ITS – FP: Are you reviewing SS from all location/code combinations for all Codes that carrying safety is required (Sites that are stocking locations) | F11: PSC-Sophia | I11: 0 | K11: no review process established | L11: 1/3 of weeks off track (no review) | M11: AITS: Are you utilizing the AITS DMS tracker to document root cause and corrective actions following weekly pit stop review? - DMS Compliance > 90% IBPI: Weekly review, preferably using dynamic review template, review completion >90% | N11: FALSE
A12: 11 | B12: Integrated Inventory Management | C12: 11 | D12: Processes | E12: ITS – FP: Do you have an up to date ITS Operating Strategy as per CBA (including exception handling), to communicate critical inventory target setting parameters supporting different business cases and supply chains. | F12: PSC-Sophia | I12: 0 | K12: no ITS operating strategy | L12: ITS Operating strategy exists but is not up to date or doesn't contain all elements as per CBA | M12: ITS strategy up to date, complete and reviewed regularly as per CBA A-ITS: - Op Strategy includes default (sys) values and exception criteria - Op Strategy is revised and updated quarterly IBPI: ITS strategy part of yearly POW (CBA: vision tab in SWP) & review triggers are to be reviewed at least Quarterly. | N12: FALSE
A13: 12 | B13: Integrated Inventory Management | C13: 12 | D13: Processes | E13: ITS – FP: Were identified safety concerns troubleshot to root cause and addressed in a timely manner? | F13: PSC-Sophia | I13: 0 | K13: no trouble shooting. | L13: no regular process to handle troubleshooting | M13: structural process to handle troubleshooting A-ITS: Is there a weekly (IP @ 100) pit stop review between SNP PE/CSP/IOL ? IBPI: is there proper pit stop structure (IP@100) as platform to raise queries, benchmark and identify opportunities. | N13: FALSE
A14: 13 | B14: Integrated Inventory Management | C14: 13 | D14: Processes | E14: ITS-RPM:Is ITS RPM review conducted on monthly basis for all supply chains ? "Quarterly If aligned" | F14: PSC-Jiawen | I14: 0 | K14: no review process established | L14: Done every 6 months | M14: Done monthly/quarterly based on BU alignment | N14: FALSE
A15: 14 | B15: Integrated Inventory Management | C15: 14 | D15: Processes | E15: ITS-RPM: Is agreed SSS aligned with the supply chain leader before upload? | F15: PSC-Jiawen | I15: 0 | K15: Not aligned | L15: 50% of PRIMA cycles alignment | M15: 100% of PRIMA cycles alignment | N15: FALSE
A16: 15 | B16: Integrated Inventory Management | C16: 15 | D16: Processes | E16: Cash RCLA: Is CASH RCLA SWP being applied in BU and the loss analysis occurred during last 12 months to feed following FY Inventory FIRM ? | F16: PSC-Sophia | I16: 0 | K16: No Cash RCLA SWP applied and no Cash RCLA session occurred in past 12 months to feed following year Inventory FIRM | L16: Cash RCLA SWP applied but no Cash RCLA session occurred in last 12 months or session occurred but not strictly following RCLA approach | M16: Cash RCLA SWP fully applied in BU and Cash RCLA session occurred in past 12 months feeding following FY Inventory FIRM | N16: FALSE
A17: 16 | B17: Integrated Inventory Management | C17: 16 | D17: Processes | E17: Cash RCLA:Is there a regular PDCA cycle that includes the measures & actions tracking ? Are the losses eliminated as per plan ? | F17: PSC-Sophia | I17: 0 | K17: No inventory PDCA in BU | L17: Inventory PDCA in place but not structurally followed, no regular drumbeat | M17: BU Inventory PDCA in place, regular drumbeat in place, actions tracking and losses eliminated as per plan | N17: FALSE
A18: 17 | B18: Integrated Inventory Management | C18: 17 | D18: Processes | E18: Cash RCLA: Are there clear Cash DOH or FCF targets for the next 3 years ahead of RCLA deployed by leadership ? | F18: PSC-Sophia | I18: 0 | K18: No clear target for BU/region deployed | L18: Target deployed but not across the 3 years | M18: Target deployed for the full three years | N18: FALSE
A19: 18 | B19: Integrated Inventory Management | C19: 18 | D19: Processes | E19: Cash RCLA: Are the loss elimination opportunities (TAPA) sufficient to meet the business requirements? | F19: PSC-Sophia | I19: 0 | K19: Action plan opportunities not meeting the business needs (less than 50%) | L19: Action plan opportunities in range of 50% - 100% of business needs (TAPA assumed) | M19: Action plan opportunities exceeding business needs (buffer in TAPA) | N19: FALSE
A20: 19 | B20: Integrated Inventory Management | C20: 19 | D20: Processes | E20: IM- UPI :Is the VS / Category tracking UPI at the bucket level on a weekly basis and communicating internally and to RBU, PSC and SMO leadership on a monthly basis, including leadership reviews? Are the defined and agreed actions sufficient to prevent the inventory gaps from reoccurring? | F20: PSC-Sophia | I20: 0 | K20: NO communication shared internally or externally to ALL UPI buckets | L20: Root causing internally on monthly only for all UPI | M20: Root causing done on weekly basis all UPI and shared with RBU & SMO on monthly basis with action plans sufficient to prevent reoccurring | N20: FALSE
A21: 20 | B21: Integrated Inventory Management | C21: 20 | D21: Processes | E21: IM- UPI: Are NPI codes >90d in Evaluation and Execution being reviewed on a weekly basis and prioritized for action planning. | F21: PSC-Yuchen | I21: 0 | K21: Overdue NPI isn't reviewed | L21: overdue NPI is reviewed on bi-weekly/Monthly | M21: Overdue NPI is reviewed on weekly basis | N21: FALSE
A22: 21 | B22: Integrated Inventory Management | C22: 21 | D22: Processes | E22: IM-UPI: Is NPI accrual done on quarterly basis following the accruals SWP | F22: PSC-Yuchen | I22: 0 | K22: Accrual process isn't done | L22: Accrual process is done but not on quarter basis | M22: Accrual is done on quarter basis following SWP | N22: FALSE
A23: 22 | B23: Integrated Inventory Management | C23: 22 | D23: Processes | E23: IM: Does the VS / Category have scheduled active reviews within the category, RBU and sites to discuss inventory/ UPI issues( Gap versus glidepath) on a weekly basis (weekly Category DDS)? AND on a monthly basis to discuss inv/ UPI issues ( Gap versus glidepath), obstacles and action plans (SNA )? | F23: PSC-Sophia | I23: 0 | K23: NO tracking on Weekly Category DDS and SNA | L23: yes , yet no action plan / root causing shared | M23: yes, root causing and action plan discussed - share documentation | N23: FALSE
A24: 23 | B24: Integrated Inventory Management | C24: 23 | D24: Processes | E24: IM: Are the Daily/Weekly VS (Value Stream), Category, and Demand/Supply DDS covering Inventory/UPI? | F24: PSC-Sophia | I24: 0 | K24: NO inventory discussed in daily basis | L24: NPI is discussed on weekly basis only and not UPI discussed or ME discussion weekly | M24: NPI discussed on daily , UPI discussed in weekly and ME discussed weekly | N24: FALSE
A25: 24 | B25: Integrated Inventory Management | C25: 24 | D25: Processes | E25: IM: Is inventory FF is conducted on monthly basis with clear targets for FP & RPM month closure ? | F25: PSC-Sophia | I25: 0 | K25: No FF conducted | L25: FF done on quarterly basis | M25: FF done on monthly basis with clear monthly targets | N25: FALSE
A26: 25 | B26: Integrated Inventory Management | C26: 25 | D26: Processes | E26: IM- Initiatives: Is the VS / Category executing the PIPO DMS as required for all their initiatives? | F26: PSC-Sophia | I26: 0 | K26: UPI not discussed in initiatives DTM D13 - PIPO codes resulting in UPI | L26: ONLY forecasted RPI hurt is discussed and not current PIPO hurt due to FCST adjustments needed from IOL | M26: UPI behind IOLs id discussed in weekly basis and action plan documented in D13 summary | N26: FALSE
A27: 26 | B27: Integrated Inventory Management | C27: 26 | D27: Processes | E27: IM- Initiative: Has the VS / Category documented Anticipation Inventory assumptions into Operating Strategy and executing it ? | F27: PSC-Sophia | I27: 0 | K27: No anticipation % set in OS | L27: Anticipation strategy set in OS and not followed in execution | M27: Anticipation strategy set in OS and followed in exception | N27: FALSE
A28: 27 | B28: Integrated Inventory Management | C28: 27 | D28: Processes | E28: IM- Initiatives: Does the VS / Category have a robust process to ensure quarterly initiative reviews to reflect as building blocks to the inventory glidepath as part of the Master Plan review and are the building blocks properly communicated and incorporated into the glidepath? | F28: PSC-Sophia | I28: 0 | K28: No quarter review for initiative | L28: Quarter review for initiative and building block set yet not added in glidepaths | M28: Quarter review for initiative done & building block and added in glidepaths | N28: FALSE
... A37: 36 | B37: Integrated Inventory Management | C37: 36 | D37: Systems | E37: IM- UPI: Is the VS / Category executing in depth analysis of top issues utilizing HIT graphs (ISC PBI) at least quarterly for FP and RPI ? | F37: PSC-Sophia | I37: 0 | K37: No hit graphs used | L37: Hit graphs used but only in cash workshops | M37: Hit graphs used on monthly basis - shared documentation , OR no hit graphs used and UPI % is single digit | N37: FALSE
A38: 37 | B38: Integrated Service | C38: 1 | D38: Results | E38: Unanalyzed cuts (Cuts root caused 7.1.1) are < 5% for at least 9 months out of the last 12 months | F38: PSC-Yuchen | I38: 0 | K38: unanalyzed cuts > 5% for last 12 months | L38: unanalyzed cuts < 5% for only 4 months out of last 12 months | M38: unanalyzed cuts <5% for at least 9 out of last 12 months | N38: FALSE
A39: 38 | B39: Integrated Service | C39: 2 | D39: Capability | E39: Are the Regional TOF Key Users in place? | F39: PSC-Cookie | I39: 0 | K39: No key user defined | L39: No key user defined | M39: Yes, Key User in place | N39: FALSE
A40: 39 | B40: Integrated Service | C40: 3 | D40: Capability | E40: Is the TOF Key User knowledge sufficient to help the Organization leverage service tools to drive appropriate action plans and insights? | F40: PSC-Cookie | I40: 0 | K40: Key user isn't supporting the organization | L40: Key user isn't fully knowledgeable about all service Tools/Work processes | M40: Key User has knowledge necessary to support the Organization. | N40: FALSE
A41: 40 | B41: Integrated Service | C41: 4 | D41: Capability | E41: Are the Leaders validating the proper use of Root Causes? And intervening where needed to address and remove the main TOF Root Causes? (For Example: Which system or Work Process failed ? Are Leaders assessing the plausibility of the proposed actions ? Are the defined and agreed actions sufficient to prevent the TOF from reoccurring?) | F41: PSC-Cookie | I41: 0 | K41: Leaders do not engage or evaluate root causes. | L41: Leaders review the root causes at a high level but do not reach for systemic/work process failures and improvements | M41: Leaders regularly review root causes at the true failure level and review action plans for plausibility and completeness. | N41: FALSE
A42: 41 | B42: Integrated Service | C42: 5 | D42: Capability | E42: Process owner defined for every work process and ensures in process/out process measures are tracked & visible (Service Management) | F42: PSC-Suz. | I42: 0 | K42: No assigned owner | L42: owner assigned but in process/out process measures not tracked | M42: Owner assigned and in process/out process measures are tracked | N42: FALSE
A43: 42 | B43: Integrated Service | C43: 6 | D43: Processes | E43: Does our Codes @ risk process happens at least once/week , covers all gaps within Supply Chain Lead time and mitigation plans are in place? | F43: PSC-Yuchen | I43: 0 | K43: No process for Codes @Risk | L43: Process happens but not weekly | M43: process happens at least once/week and mitigation plans being worked to all FPCs on risk | N43: FALSE
A44: 43 | B44: Integrated Service | C44: 7 | D44: Processes | E44: Is critical Code List (FPCs with gaps against orders in coming 2-3 days) being shared & actioned 100% or as per market defined threshold on daily basis? | F44: PSC-Yuchen | I44: 0 | K44: critical code list not shared/actioned | L44: critical code list not shared daily or not 100% actioned/not meeting market defined threshold | M44: critical code list shared daily and 100% actioned/as per Market defined threshold | N44: FALSE
A45: 44 | B45: Integrated Service | C45: 8 | D45: Processes | E45: Does the OU has defined PACE for escalation, escalation threshold agreed and action plans triggered after escalation | F45: PSC-Yuchen | I45: 0 | K45: No PACE/Escalation threshold defined | L45: PACE,Triggers and escalation process defined but not being consistently followed | M45: PACE is defined and action plans are triggered upon escalation | N45: FALSE
A46: 45 | B46: Integrated Service | C46: 9 | D46: Processes | E46: Are the TOF weekly or monthly action plans documented, reviewed, and made available to all parties/posted online with link to document? | F46: PSC-Cookie | I46: 0 | K46: No, all plans were not documented, not reviewed, and/or not uploaded | L46: Monthly plans only are reviewed & documented | M46: Monthly & weekly plans documented, reviewed and uploaded | N46: FALSE
A47: 46 | B47: Integrated Service | C47: 10 | D47: Processes | E47: Are the regional hypercare guidelines and triggers being applied and used consistently? | F47: PSC-Yuchen | I47: 0 | K47: No hypercare guidelines or triggers defined or used | L47: Guidelines and triggers identified but not consistently followed | M47: Guidelines and triggers identified and consistently followed | N47: FALSE
A48: 47 | B48: Integrated Service | C48: 11 | D48: Processes | E48: Are exceptions (restatements) and exclusions to TOF results being done using the PACE model as outlined in the TOF CBA? | F48: PSC-Cookie | I48: 0 | K48: No, the PACE was not followed for any exception or exclusion | L48: PACE is sometimes not followed | M48: PACE is always followed for any exceptions or exclusions | N48: FALSE
A49: 48 | B49: Integrated Service | C49: 12 | D49: Systems | E49: Do you use standard global reporting tool or regional aligned tool for tracking & rootcausing TOF? | F49: PSC-Cookie | I49: 0 | K49: Not using any standard/aligned tool | L49: Using aligned tool for tracking but rootcausing is done offline | M49: Tracking & root causing are done on standard/aligned tool | N49: FALSE
A50: 49 | B50: Production Capacity | C50: 1 | D50: Results | E50: DFV - Is % difference FYTD average between BW demand hub and planning system < 2% over 18 Months ? | F50: PSC-Huarong | G50: Difference of BW Demand Hub and Planning System FYTD <2% over 18 months，detail scorecard refer to the DFV result update email | I50: 2 | K50: No Tracking measure' | L50: Difference of BW Demand Hub and Planning System FYTD >2% and < 5% over 18 months | M50: Difference of BW Demand Hub and Planning System FYTD <2% over 18 months | N50: FALSE
A51: 50 | B51: Production Capacity | C51: 2 | D51: Results | E51: ALL except NA: Production C:D compliance above 90% for the next 18 months for all the resources identified as critical NA only: No RCCP resources identified as critical with 1) 2 or more months with CtD < 1.0 or 2) More than 10% of total production requirements volume is below CtD target (Months 2-17, for both Balanced 50/50 and High Side scenarios) | F51: PSC-Initial | I51: 0 | K51: All except NA:C:D Compliance not measured NA only: Not measuring 1) When CtD < 1.0 for 2 or more months or 2) More than 10% of total production requirements volume is below CtD target | L51: All except NA: C:D compliance measured but < 90% over 18 months NA only: At least 1 RCCP resource with 1) 2 or more months with CtD < 1.0 or 2) More than 10% of total production requirements volume is below CtD target | M51: All except NA: C:D compliance > 90% next 18 months NA only: No RCCP resource with 1) 2 or more months with CtD < 1.0 or 2) More than 10% of total production requirements volume is below CtD target | N51: FALSE
A52: 51 | B52: Production Capacity | C52: 3 | D52: Capability | E52: Do all Supply Chains have an identified DFV owner in place and fully trained? | F52: PSC-Suz. | I52: 0 | K52: Does not have all owners identified | L52: Has owners identified but not fully trained | M52: All SC's have owner in place & fully trained: A documented succession plan exists sustaining capability/business continuity. The BU has suffered no losses or erosion or slowdown of results related to staffing or training issues | N52: FALSE
A53: 52 | B53: Production Capacity | C53: 4 | D53: Capability | E53: Do all RCCP families have an identified RCCP owner in place & fully trained? | F53: PSC-Suz. | I53: 0 | K53: Does not have all owners identified | L53: Has owners identified but not fully trained | M53: All RCCP families have owner in place & fully trained: A documented succession plan exists sustaining capability/business continuity. The BU has suffered no losses or erosion or slowdown of results related to staffing or training issues | N53: FALSE
A54: 53 | B54: Production Capacity | C54: 5 | D54: Capability | E54: Process owner defined for every work process and ensures in process/out process measures are tracked & visible (RCCP & DFV) | F54: PSC-Suz. | I54: 0 | K54: No assigned owner | L54: owner assigned but in process/out process measures not tracked | M54: Owner assigned and in process/out process measures are tracked | N54: FALSE
A55: 54 | B55: Production Capacity | C55: 6 | D55: Processes | E55: DFV SWP being followed according to the PMC | F55: PSC-Huarong | G55: DFV process follow the global standard working process to excute including the tool/Issue identify/action plan and owner identify. | I55: 2 | K55: Not following SWP | L55: SWP partially followed | M55: SWP fully followed: Checking validation report weekly for differences in the demand flow from Demand Planning system (BW Demand HUB) to Supply Planning systems (e.g. APO DRP, SAP DRP, SAP R3), then working to resolve errors, following a documented process | N55: FALSE
A56: 55 | B56: Production Capacity | C56: 7 | D56: Processes | E56: If you have Global Supply Chains (GSC): Is DFV process in place? | F56: PSC-Huarong | G56: We also cover the HKTW score,follow the same standard to excute. | I56: 2 | K56: No process in place | L56: Partial process in place | M56: Full process in place or don't have GSC (For Global Supply Chains, the CSP in the Destination Region performs DFV) | N56: FALSE
A57: 56 | B57: Production Capacity | C57: 8 | D57: Processes | E57: RCCP SWP being followed according to the RCCP PMC | F57: PSC-Chang | I57: 0 | K57: Not following SWP | L57: SWP partially followed | M57: SWP fully followed RCCP's done on all critical Making & Packing constraints All critical constraints from other nodes (Supplier, T&W) are incorporated into Production RCCP plans All Critical constraints have a monthly RCCP process, In monthly buckets and goes out 18 months All Capacity & Demand Below the Line are being added in | N57: FALSE
A58: 57 | B58: Production Capacity | C58: 9 | D58: Processes | E58: RCCP data inputs are coming from the source system | F58: PSC-Chang | I58: 0 | K58: Not using source system as starting point for capacity & demand data | L58: Not fully using source system as starting point for capacity & demand data but using source system to confirm capacity & demand values are in range with the source system | M58: Fully using source system as starting point for capacity & demand data including pulling the data the week after the official BOP Pass weekend Using Production Requirements (From planning system) as the Demand starting point & using Intervals of Available capacity (from planning system) as the Capacity Starting point Capacity Parameters maintained for the RCCP model are based on demonstrated rates, actual staffed operating hours / weeks, plant calendar days. These parameters are documented, and reviewed at least quarterly | N58: FALSE
A59: 58 | B59: Production Capacity | C59: 10 | D59: Processes | E59: Identification of recommended C:D targets is complete | F59: PSC-Chang | I59: 0 | K59: No annual process in place | L59: Annual process in place but not using the CtD target setting tool/aligned OU tool | M59: Annual process in place & using standard tool: Reviewed Annually for all RCCP families. CSNP recommendations are communicated to the BP for input into aligned to CtD target that is included in the Operating Strategy Running new CtD target setting solution (AI Apps) or another aligned standard statistical tools to get recommended CtD for each RCCP family | N59: FALSE
A60: 59 | B60: Production Capacity | C60: 11 | D60: Processes | E60: Is there a 50/50 & High Side forecast scenario done for all RCCP Families each month? | F60: PSC-Chang | I60: 0 | K60: Neither 50/50 or High side RCCP being completed | L60: Only doing 50/50 RCCP: Assumptions are documented regarding Demand / Volume used as inputs for the RCCP volume | M60: Doing both 50/50 & High Side: Assumptions are documented regarding Demand / Volume used as inputs for the RCCP volume Other "what if's" besides High Side are evaluated as needed | N60: FALSE
A61: 60 | B61: Production Capacity | C61: 12 | D61: Processes | E61: RCCP issues or deviations from Operating strategy are getting discussed & resolved in SNA? | F61: PSC-Chang | I61: 0 | K61: RCCP Risks not being discussed in SNA | L61: Capacity related issues or Operating Strategy deviations (service, inventory, etc.) are being discussed in SNA but no clear plan to reduce risks | M61: RCCP risks are talked and clear plan to reduce risks aligned & shared Capacity related issues or Operating Strategy deviations (service, inventory, etc.) are being discussed in SNA including options and an aligned plan to eliminate or resolve capacity risk is completely All parties affected by decision (PSM, Warehouse, Transportation, etc.) are informed Any aligned changes to the plan (Pre-build, sourcing changes, overtime, etc.) should be added to the Planning Systems of Record to let the systems plan accordingly, where applicable | N61: FALSE
A62: 61 | B62: Production Capacity | C62: 13 | D62: Processes | E62: For Global Supply Chains: Are RCCP’s aggregated across regions for clear view of overall C:D | F62: PSC-Chang | I62: 0 | K62: No process in place | L62: Partial process in place for RCCP’s aggregated across regions for clear view of overall C:D | M62: Full process in place (RCCP’s aggregated across regions for clear view of overall C:D) or don't have GSC | N62: FALSE
A63: 62 | B63: Production Capacity | C63: 14 | D63: Systems | E63: CSNP is using the standard Demand Flow Verification CSP-BW report | F63: PSC-Chang | I63: 0 | K63: Not using standard report | L63: No 1 score for this question | M63: Using standard report: APO-DRP BU's: DRP Forecast Flow Validation Report (FFVR) Non APO-DRP BU's: G-CSP-AO-Demand Flow Verification (DFV) report | N63: FALSE
A64: 63 | B64: Production Capacity | C64: 15 | D64: Systems | E64: CSNP is using an aligned RCCP solution | F64: PSC-Chang | I64: 0 | K64: Not using standard solution | L64: No 1 score for this question | M64: Using aligned to solution: RCCP workbooks in Rapid response, Standard CSP-BW report or another aligned to RCCP solution (approved by Global RCCP Process Leader) | N64: FALSE
A65: 64 | B65: Supply Chain Orchestration | C65: 1 | D65: Results | E65: 2 of supply chain nodes DBNX gaps are improving vs. YA or meeting RBU glide path: DNBD vs. DBNC, DBNR vs. DBNS (or DBNO), DBNI vs. DBNO DC. | F65: HP/TC/XQ Plant SNP Ziwei/Jason/Matt | I65: 0 | K65: No DBNX gap is improving vs. YA or meeting RBU glide path | L65: 1 DBNX gap is improving vs. YA or meeting RBU glide path | M65: 2 DBNXs gaps are improving vs. YA or meeting RBU glide path | N65: FALSE
A66: 65 | B66: Supply Chain Orchestration | C66: 2 | D66: Results | E66: MPS - Is MPS Output measure consistently being tracked as per PMC and delivered vs sites IWS phase targets? | F66: HP/TC/XQ Plant SNP Ziwei/Jason/Matt | I66: 0 | K66: PMC is not fully applied and output measure is not always consistently tracked and delivered | L66: PMC is fully applied and output measure is not always consistently tracked and delivered | M66: PMC is fully applied and output measure is consistently tracked and delivered | N66: FALSE
A67: 66 | B67: Supply Chain Orchestration | C67: 3 | D67: Capability | E67: Staffing - Are all PSC Category CNL/CNA/CSNP Leader, and Manf. Site SNO/SNP Leader(s) Roles filled? | F67: HP/TC/XQ Plant SNP Ziwei/Jason/Matt & PSC Suz. | I67: 0 | K67: All (PSC and Manufacturing Site) Roles are not staffed. | L67: 50% of (PSC and Manufacturing Site) Roles are staffed. | M67: All (PSC and Manufacturing Site) Roles are staffed. | N67: FALSE
A68: 67 | B68: Supply Chain Orchestration | C68: 4 | D68: Capability | E68: CNL/CNA/CSNP Resources Qualification is a Priority to ensure business continuity especially during transitions | F68: HP/TC/XQ Plant SNP Ziwei/Jason/Matt & PSC Suz. | I68: 0 | K68: No Skills Matrix Tracking is established reflecting by individual qualification status vs Global role QLM. | L68: Skills Matrix Tracking is established reflecting by individual qualification status vs Global role QLM. 70% of the OU CNL/CNA/CSNP resources are qualified minimum Basic as per Global QLM requirements at any point in time (can run the business and also covers for org seniority during transitions) | M68: Skills Matrix Tracking is established reflecting by individual qualification status vs Global role QLM. 70% of OU CNL/CNA/CSNP are qualified minimum Basic as per Global QLM requirements at any point in time (can run the business and also covers for org seniority during transitions) 40% of employees are qualified Intermediate as per Global QLM requirements at any point in time | N68: FALSE
A69: 68 | B69: Supply Chain Orchestration | C69: 5 | D69: Capability | E69: Process owner defined for every work process and ensures in process/out process measures are tracked & visible (MPS,DDS,POSS, PCL & POW) | F69: HP/TC/XQ Plant SNP Ziwei/Jason/Matt & PSC Suz. | I69: 0 | K69: owner assigned but in process/out process measures not tracked | L69: Owner assigned and in process/out process measures are tracked | M69: Owner assigned and in process/out process measures are tracked | N69: FALSE
A70: 69 | B70: Supply Chain Orchestration | C70: 6 | D70: Capability | E70: IR - Is Operations team trained on using the Issue Resolution template at least annually? Training Sessions or e-mail refreshers can be used to make sure the team enabled with the right capability and tools to communicate and solve issues effectively | F70: PSC-Cookie | I70: 0 | K70: Neither training has been conducted within Category Operations team nor refreshers are being used. | L70: Training has been done once since more than 1 year. | M70: Annual training is being done annually within Category Operations team or refreshers is being sent out throughout the year. | N70: FALSE
A71: 70 | B71: Supply Chain Orchestration | C71: 7 | D71: Capability | E71: MPS - Is MPS System Owner & Department DMS Owners trained and qualified (as per SUC at right proficiency level)? | F71: HP/TC/XQ Plant SNP Ziwei/Jason/Matt/Xiaoye | I71: 0 | K71: System Owner & Department DMS Owners are not trained and not qualified yet | L71: System Owner is trained and qualified with SUC but Department Owners are not trained and qualified or vice versa | M71: System Owner & Department DMS owners are trained and qualified with SUC at right proficiency level by Qualified assessor | N71: FALSE
A72: 71 | B72: Supply Chain Orchestration | C72: 8 | D72: Capability | E72: POSS - All relevant triggers/roles & back up roles are defined with measurable conditions and the team executed those triggers per defined conditions and PACE model | F72: HP/TC/XQ Plant SNP Ziwei/Jason/Matt | I72: 0 | K72: Less than 50% of roles fulfilled | L72: Less than 80% of roles fulfilled | M72: All roles fulfilled | N72: FALSE
A73: 72 | B73: Supply Chain Orchestration | C73: 9 | D73: Capability | E73: PCL - Does your RBU has an owner assigned to lead parameter center-lining work, who is trained on E2E Planning Parameter Centerline PDCA, qualified on PCL SUC, can explain the fundamentals of parameter, can explain the key concept and definition of critical parameters? | F73: PSC-Suz. | I73: 0 | K73: PCL Key User not assigned | L73: PCL Key user assigned but not qualified | M73: PCL Key user assigned & qualified | N73: FALSE
A74: 73 | B74: Supply Chain Orchestration | C74: 10 | D74: Capability | E74: POW - Is there a qualified POW facilitator in place to enable quality POW execution? & the key participants trained on POW CBA, understand the role of POW in the E2E Operating Strategy process, knows the difference between POW and Parameter Loss Analysis Workshop, and can explain the inputs and outputs of a POW? | F74: PSC-Suz. | I74: 0 | K74: No POW facilitator is in place & key participants are not trained on POW CBA | L74: POW facilitator is in place but key participants are not trained on POW CBA or vice versa | M74: POW facilitator is in place & key participants are trained on POW CBA | N74: FALSE
A75: 74 | B75: Supply Chain Orchestration | C75: 11 | D75: Capability | E75: SCSI - Does your RBU have a SCSI "go-to person" identified (e.g. Sync Leader, Key User) and qualified per SCSI Step-Up-Card to enable and sustain RBU's SCSI capability? | F75: PSC-Suz. | I75: 0 | K75: SCSI Key user not assigned | L75: SCSI Key user assigned but not qualified | M75: SCSI Key use assigned & qualified | N75: FALSE
A76: 75 | B76: Supply Chain Orchestration | C76: 12 | D76: Capability | E76: IWS - Are all E2E VS at their targeted measures based on current IWS Phase (SCCA/SNP WAP)? | F76: HP/TC/XQ Plant SNP Ziwei/Jason/Matt & PSC Suz. | I76: 0 | K76: All E2E VS measures are not at their target as per IWS Phase | L76: 50% of E2E VS measures are at their target as per IWS Phase | M76: All E2E VS measures are at the BU target IWS phase | N76: FALSE
A77: 76 | B77: Supply Chain Orchestration | C77: 13 | D77: Processes | E77: IR - Is issue resolution handled through Decision Sheets covering key IR elements to drive resolution in a timely manner, following the Category Operating Strategy Principles? | F77: PSC-Cookie | I77: 0 | K77: No decision sheets are being used in the category | L77: Non-standard decision sheets are used to take decisions | M77: Standard decision sheets are used indicating clear risk on service/cash/cost for the category | N77: FALSE
A78: 77 | B78: Supply Chain Orchestration | C78: 14 | D78: Processes | E78: MPS - Are MPS in-process measures at target/within limits (as per PMC)? | F78: HP/TC/XQ Plant SNP Ziwei/Jason/Matt/Xiaoye | I78: 0 | K78: PMC is not fully applied whatever is the result of in-process measures | L78: PMC is fully applied and in-process measures are not at target/within limits | M78: PMC is fully applied and in-process measures are at target/within limits | N78: FALSE
A79: 78 | B79: Supply Chain Orchestration | C79: 15 | D79: Processes | E79: MPS - Are 100% of unadjusted MPS misses properly analyzed and root caused | F79: HP/TC/XQ Plant SNP Ziwei/Jason/Matt/Xiaoye | I79: 0 | K79: <80% of unadjusted misses are properly analyzed and root caused | L79: <90% of unadjusted misses are properly analyzed and root caused | M79: 100% of unadjusted misses are properly analyzed and root caused | N79: FALSE
A80: 79 | B80: Supply Chain Orchestration | C80: 16 | D80: Processes | E80: MPS - Are MPS measures reviewed during all steps of DDS cycle (Shift Handover, Line DDS, Planning/Manufacturing DDS (D2))? | F80: HP/TC/XQ Plant SNP Ziwei/Jason/Matt/Xiaoye | I80: 0 | K80: Measures are not reviewed during all steps of DDS cycle | L80: Measures are not constantly reviewed during all steps of DDS cycle (review during some steps is missing) | M80: Measures are constantly reviewed during all steps of DDS cycle | N80: FALSE
A81: 80 | B81: Supply Chain Orchestration | C81: 17 | D81: Processes | E81: MPS - Is MPS PDCA process in place and working as designed (focus on a formal review process with leadership and a continuous improvement action plan)? | F81: HP/TC/XQ Plant SNP Ziwei/Jason/Matt/Xiaoye | I81: 0 | K81: DMS is not managed with PDCA, plans are unreliable and review with leadership is missing/incomplete to manage reliable gap analysis/action plan | L81: DMS is managed with PDCA with unreliable Plans, Do, Check and Act steps detected and/or leadership reviews and/or insufficient gap analysis and action plan | M81: DMS is fully managed with PDCA with clear Plans, Do, Check and Act review with leadership reviews to develop solid gap analysis and action plan (as per PMC) | N81: FALSE
A82: 81 | B82: Supply Chain Orchestration | C82: 18 | D82: Processes | E82: MPS - Are MPS measures revised reviewed and aligned with PSC (as per PMC)? | F82: HP/TC/XQ Plant SNP Ziwei/Jason/Matt/Xiaoye | I82: 0 | K82: Measures are not constantly revised reviewed by System Owner with PSC counterpart as per PMC | L82: Measures are constantly revised reviewed by System Owner with PSC counterpart as per PMC but gap analysis and action plan are missing or incomplete | M82: Measures are constantly revised reviewed by System Owner with PSC counterpart as per PMC with gap analysis and action plan | N82: FALSE
A83: 82 | B83: Supply Chain Orchestration | C83: 19 | D83: Processes | E83: MPS - Is SNP scorecard updated with all MPS measures & correct targets as per IWS Phase and reviewed at least on quarterly basis? | F83: HP/TC/XQ Plant SNP Ziwei/Jason/Matt/Xiaoye | I83: 0 | K83: Scorecard is not always updated with all measures and/or not always reviewed with insufficient gap analysis and action plan | L83: Scorecard is updated with all measures but not always reviewed or with insufficient gap analysis and action plan | M83: Scorecard is updated and reviewed with all measures with gap analysis and action plan | N83: FALSE
A84: 83 | B84: Supply Chain Orchestration | C84: 20 | D84: Processes | E84: DDS - Are the action plans updated prior the DDS (follow-ups from previous meeting + new known issues added + Actions are updated)? If no current actions because of no issues, check action plan history to confirm action planning is done. This is applicable to D1,D2,D3,D5 & D7 | F84: HP/TC/XQ Plant SNP Ziwei/Jason/Matt/Xiaoye for D2, PSC Initial/Cookie/Suz. for D1/D3/D5/D7 | I84: 0 | K84: No action plan exists. | L84: 1 or More Action items exists with due date today or in the past and not resolved yet | M84: All Action Items have dates in the future and are reviewed with the same frequency as the DDS | N84: FALSE
A85: 84 | B85: Supply Chain Orchestration | C85: 21 | D85: Processes | E85: DDS - Are ALL off-track measures being action planned during the DDS? | F85: HP/TC/XQ Plant SNP Ziwei/Jason/Matt/Xiaoye for D2, PSC Initial/Cookie/Suz. for D1/D3/D5/D7 | I85: 0 | K85: Off-Track in-process measures not actioned | L85: 50% of off-track in-process measures are actioned | M85: All Off-Track in-process measures are actioned | N85: FALSE
A86: 85 | B86: Supply Chain Orchestration | C86: 22 | D86: Processes | E86: DDS - Are the mandatory attendees - as per the CBA - the only participants of the meeting? | F86: HP/TC/XQ Plant SNP Ziwei/Jason/Matt/Xiaoye for D2, PSC Initial/Cookie/Suz. for D1/D3/D5/D7 | I86: 0 | K86: 1 or more Mandatory Attendee are not regularly attending | L86: All mandatory attendees are regularly attending but 1 or More Non-Mandatory Attendee (not regularly) attending the meeting without adding value | M86: Only mandatory attendees are in the meeting, with clear ownership of their respective measures OR 1 or More Non-Mandatory Attendee attending the meeting but clearly adding value. | N86: FALSE
A87: 86 | B87: Supply Chain Orchestration | C87: 23 | D87: Processes | E87: DDS - Preparation - Are the latest measures actuals completed in the review tool before the meeting? | F87: HP/TC/XQ Plant SNP Ziwei/Jason/Matt/Xiaoye for D2, PSC Initial/Cookie/Suz. for D1/D3/D5/D7 | I87: 0 | K87: More than 2 measures have no data filled | L87: Maximum of 2 Measures not filled | M87: ALL in-process measures are filled | N87: FALSE
A88: 87 | B88: Supply Chain Orchestration | C88: 24 | D88: Processes | E88: DDS - Are the Targets & Escalation Triggers documented and known by respective measure owners? Are targets shown in the review tool next to the actual results? | F88: HP/TC/XQ Plant SNP Ziwei/Jason/Matt/Xiaoye for D2, PSC Initial/Cookie/Suz. for D1/D3/D5/D7 | I88: 0 | K88: More than 2 Measures have no clear targets or their targets are not shown in the review tool next to the actuals. | L88: Maximum of 2 Measures have no clear targets or their targets are not shown in the review tool next to the actuals. | M88: ALL in-process measures have clear targets and target owners know where the targets are originating from and their targets are not shown in the review tool next to the actuals. | N88: FALSE
A89: 88 | B89: Supply Chain Orchestration | C89: 25 | D89: Processes | E89: DDS - Does the DDS review ALL and ONLY the standard measures as per the CBA? | F89: HP/TC/XQ Plant SNP Ziwei/Jason/Matt/Xiaoye for D2, PSC Initial/Cookie/Suz. for D1/D3/D5/D7 | I89: 0 | K89: Not all Standard Measures as per the CBA are reviewed. | L89: All Standard Measures as per the CBA are reviewed AND DDS discusses NON-Standard measures that have NOT been aligned with the HPN RPL | M89: All Standard Measures as per the CBA are reviewed AND (if applicable) DDS discusses NON-Standard measures that have been aligned with the HPN RPL - written alignment including rational required. | N89: FALSE
A90: 89 | B90: Supply Chain Orchestration | C90: 26 | D90: Processes | E90: DDS - Is the DDS frequency as per the CBA [Daily/Weekly/Monthly/Quarterly]? | F90: HP/TC/XQ Plant SNP Ziwei/Jason/Matt/Xiaoye for D2, PSC Initial/Cookie/Suz. for D1/D3/D5/D7 | I90: 0 | K90: DDS Frequency is missed >10% of the times Example: if frequency is Daily, the DDS gets missed 3 Days within 25 WDs in a month | L90: DDS Frequency is missed <10% of the times Example: if frequency is Daily, the DDS gets missed 3 Days within 25 WDs in a month | M90: DDS is happening as per the correct frequency all the time | N90: FALSE
... A111: 110 | B111: Supply Chain Orchestration | C111: 47 | D111: Systems | E111: PCL- Is the E2E Parameter Centerline tool leveraged to support the execution of operating strategy execution, include planning orchestration workshop preparation, execution, and ongoing governance to enable identification of losses/opportunities? | F111: PSC-Suz. | I111: 0 | K111: No workshop done | L111: Workshop done with no clear action plan | M111: Workshop done with clear action plan using E2E PCL tool | N111: FALSE

Sheet FY2425 CSNP HC Question & Owner
A1: Assessment | B1: No | C1: Section | D1: Question | E1: Owner | F1: Rationale/Supporting for Scoring | G1: Score | H1: Criteria for Score 0 | I1: Criteria for Score 1 | J1: Criteria for Score 2 | K1: Link to SWP Benchmarking FY2324 Question & SHA
A2: Integrated Inventory Management | B2: 1 | C2: Results | D2: ITS-FP & RPM: Situational Safety less than or equal 2% average FYTD or as per BU aligned glidepaths ? | E2: PSC-Sophia | H2: Not on target for RPM and FP | I2: Results on track for one ( FP or RPM only ) | J2: Results on track for both FP and RPM | K2: IM
A3: Integrated Inventory Management | B3: 2 | C3: Results | D3: IM- UPI: % UPI and Glide path (remainder of the FY) is on or below BU target for the current FY | E3: PSC-Sophia | H3: No Glidepaths identified and UPI off track | I3: UPI Glidepaths set and UPI on track only for FP or RPM | J3: UPI Glidepaths set and UPI on track for both FP and RPM FYTD | K3: IM
A4: Integrated Inventory Management | B4: 3 | C4: Results | D4: IM: Is the evaluation for NPI is performed within 90 days of NPI is identified? Is the action plan for disposal or depletion of NPI physically executed within 90 days after evaluated? | E4: PSC-Yuchen | H4: NPI is not evaluated fully within 90 days & NPI is not disposed fully within 90 days after evaluation across the RBU. | I4: NPI evaluated fully within 90 Days or NPI disposed fully within 90 days after evaluation across the RBU. | J4: NPI is evaluated fully within 90 days and NPI is disposed fully within 90 days after evaluation across the RBU | K4: IM
A5: Integrated Inventory Management | B5: 4 | C5: Capability | D5: ITS – FP: ITS Users are able to run scenarios to investigate impacts of supply chain changes or parameter changes into Safety calculations | E5: PSC-Ann | H5: missing capability to use what ifs | I5: BU choices done without using what ifs (even though capability exists) | J5: tool what if fully leveraged A-ITS - Is the SNP PE capable of running scenarios with minimal or zero help? - Does the scenario outputs require Operational Strategy updates? IBPI: Manual triggering of IBPI engine to reflect changes of masterdata, active participation in tests improving tool | K5: ITS
A6: Integrated Inventory Management | B6: 5 | C6: Capability | D6: ITS – FP& RPM : Are all KU or/and system owners qualified within 6 months from starting role? | E6: PSC-Ann for FP, Jiawen for RM | H6: KU not trained and qualified within 6 months | I6: KU qualified but after 6 months in the role [SUC Targets end users as basic / Key users as Intermediate – CSNP/SNP PE is targeted as a KU] | J6: KU trained and qualified within 6 months in the role A-ITS - Is the SNP PE trained and qualified within first 6 months. IBPI& Prima: IBPI KU trained and qualified within first 6 months [SUC Targets end users as basic / Key users as Intermediate – CSNP/SNP PE is targeted as a KU] | K6: ITS
A7: Integrated Inventory Management | B7: 6 | C7: Capability | D7: IM- Leadership: Are the Regional inventory solutions Key Users in place and qualified by Regional BPX via the Step Up Card? | E7: PSC-Sophia | H7: No IM Keyuser assigned | I7: Inventory keyuser assigned but not qualified on IM SUC | J7: Inventory keyuser assigned and qualified with IM SUC | K7: IM
A8: Integrated Inventory Management | B8: 7 | C8: Capability | D8: Cash RCLA: Is there a Loss Analysis Leader identified for the RBU and is qualified on RCLA Step Up Card ? | E8: PSC-Sophia | H8: No BU Inventory RBU Leader assigned | I8: RBU Inventory Leader assigned but not qualified on Cash RCLA SUC | J8: RBU Inventory Leader assigned and qualified with Cash RCLA SUC | K8: Cash RCLA
A9: Integrated Inventory Management | B9: 8 | C9: Capability | D9: Process owner defined for every work process and ensures in process/out process measures are tracked & visible | E9: PSC-Yan | H9: No assigned owner | I9: owner assigned but in process/out process measures not tracked | J9: Owner assigned and in process/out process measures are tracked | K9: Capability
A10: Integrated Inventory Management | B10: 9 | C10: Capability | D10: IM - UPI:Is there any physical NPI exceeding 180 days ? Is exception granted from B4 F&A ? | E10: PSC-Yuchen | H10: There's physical NPI >180 and no exception granted | I10: There's physical NPI > 180 and all has exception granted | J10: NO physical NPI more than 180 days | K10: IM
A11: Integrated Inventory Management | B11: 10 | C11: Processes | D11: ITS – FP: Was standard PACE model and SWP followed throughout the process? | E11: PSC-Ann | H11: process not followed (no review process established, no writeback using standard tool, no owner for BU assigned to work on safety) | I11: some of elements of SWP not applied (like owner not in CSNP team, HPPP manually in planning system, and for IBPI IOPT not incorporated) | J11: All elements working which is proved by results A-ITS P - SNP PE A - SCL C - SCL, IOL, CSP, SIP E - SNP PE, SIP IBPI: weekly process, led by CNA team, Review process done (preferably with dynamic review), end users' business knowledge pulled (preferably inside IBPI, but can be offline), safety on aggregate level in line with glidepath, HPPP done inside IBPI, IOPT linkage opened for 90% of matlocs | K11: ITS
A12: Integrated Inventory Management | B12: 11 | C12: Processes | D12: ITS FP: Is master data in ITS tool correct and verified on weekly basis, including parameters coming from ITS operating strategy | E12: PSC-Ann | H12: no audit | I12: partial, not regular audit | J12: weekly auditA-ITS: - 0 APO Layer 1 - 0 Network Completeness errors - 99.8% Overall Centerline IBPI: At least mandatory elements are captured in MD checks: - production details, IOPT publishing rate, decision where to store safety + all elements required based on ITS strategy | K12: ITS
A13: Integrated Inventory Management | B13: 12 | C13: Processes | D13: ITS – FP: Are you reviewing SS from all location/code combinations for all Codes that carrying safety is required (Sites that are stocking locations) | E13: PSC-Ann | H13: no review process established | I13: 1/3 of weeks off track (no review) | J13: results on track full year A-ITS: Weekly review between SNP PE/CSP/IOL IBPI: Weekly review, preferably using dynamic review template, review completion >90% | K13: ITS
... A52: Production Capacity Management | B52: 1 | C52: Results | D52: DFV - Is % difference between BW demand hub and planning system < 2% over 18 Months? | E52: PSC-Ann | H52: DFV process not done/No Tracking measure | I52: Tracking measure but off track one or both metrics: All BU's: Difference of BW Demand Hub and Planning System < 2% over 18 months APO-DRP BU's: All errors are actively being worked weekly to be resolved Non APO-DRP BU's: All code/sites flowing over the next 13 weeks | J52: Tracking and 2 metrics on track: All BU's: Difference of BW Demand Hub and Planning System < 2% over 18 months APO-DRP BU's: All errors are actively being worked weekly to be resolved Non APO-DRP BU's: All code/sites flowing over the next 13 weeks | K52: DFV
A53: Production Capacity Management | B53: 2 | C53: Results | D53: Production C:D compliance above 90% for the next 18 months for all the resources identified as critical | E53: PSC-Initial | G53: 2 | H53: C:D Compliance not measured | I53: C:D compliance measured but < 90% over 18 months | J53: C:D compliance > 90% next 18 months | K53: RCCP
A54: Production Capacity Management | B54: 3 | C54: Capability | D54: Do all Supply Chains have an identified DFV owner in place and fully trained? | E54: PSC-Yan | H54: Does not have all owners identified | I54: Has owners identified but not fully trained | J54: All SC's have owner in place & fully trained: A documented succession plan exists sustaining capability/business continuity. The BU has suffered no losses or erosion or slowdown of results related to staffing or training issues | K54: Capability
A55: Production Capacity Management | B55: 4 | C55: Capability | D55: Do all RCCP families have an identified RCCP owner in place & fully trained? | E55: PSC-Yan | H55: Does not have all owners identified | I55: Has owners identified but not fully trained | J55: All RCCP families have owner in place & fully trained: A documented succession plan exists sustaining capability/business continuity. The BU has suffered no losses or erosion or slowdown of results related to staffing or training issues | K55: Capability
A56: Production Capacity Management | B56: 5 | C56: Capability | D56: Process owner defined for every work process and ensures in process/out process measures are tracked & visible | E56: PSC-Yan | H56: No assigned owner | I56: owner assigned but in process/out process measures not tracked | J56: Owner assigned and in process/out process measures are tracked | K56: Capability
A57: Production Capacity Management | B57: 6 | C57: Processes | D57: DFV SWP being followed according to the PMC | E57: PSC-Ann | H57: Not following SWP | I57: SWP partially followed | J57: SWP fully followed: Checking validation report weekly for differences in the demand flow from Demand Planning system (BW Demand HUB) to Supply Planning systems (e.g. APO DRP, SAP DRP, SAP R3), then working to resolve errors, following a documented process | K57: DFV
A58: Production Capacity Management | B58: 7 | C58: Processes | D58: If you have Global Supply Chains (GSC): Is DFV process in place? | E58: PSC-Ann | H58: No process in place | I58: Partial process in place | J58: Full process in place or don't have GSC (For Global Supply Chains, the CSP in the Destination Region performs DFV) | K58: DFV
A59: Production Capacity Management | B59: 8 | C59: Processes | D59: RCCP SWP being followed according to the RCCP PMC | E59: PSC-Chang | H59: Not following SWP | I59: SWP partially followed | J59: SWP fully followed RCCP's done on all critical Making & Packing constraints All critical constraints from other nodes (Supplier, T&W) are incorporated into Production RCCP plans All Critical constraints have a monthly RCCP process, In monthly buckets and goes out 18 months All Capacity & Demand Below the Line are being added in | K59: RCCP
A60: Production Capacity Management | B60: 9 | C60: Processes | D60: RCCP data inputs are coming from the source system | E60: PSC-Chang | H60: Not using source system as starting point for capacity & demand data | I60: Not fully using source system as starting point for capacity & demand data but using source system to confirm capacity & demand values are in range with the source system | J60: Fully using source system as starting point for capacity & demand data including pulling the data the week after the official BOP Pass weekend Using Production Requirements (From planning system) as the Demand starting point & using Intervals of Available capacity (from planning system) as the Capacity Starting point Capacity Parameters maintained for the RCCP model are based on demonstrated rates, actual staffed operating hours / weeks, plant calendar days. These parameters are documented, and reviewed at least quarterly | K60: RCCP
A61: Production Capacity Management | B61: 10 | C61: Processes | D61: Identification of recommended C:D targets is complete | E61: PSC-Chang | H61: No annual process in place | I61: Annual process in place but not using the CtD target setting tool/aligned OU tool | J61: Annual process in place & using standard tool: Reviewed Annually for all RCCP families. CSNP recommendations are communicated to the BP for input into aligned to CtD target that is included in the Operating Strategy Running new CtD target setting solution (AI Apps) or another aligned standard statistical tools to get recommended CtD for each RCCP family | K61: RCCP
A62: Production Capacity Management | B62: 11 | C62: Processes | D62: Is there a 50/50 & High Side forecast scenario done for all RCCP Families each month? | E62: PSC-Chang | H62: Neither 50/50 or High side RCCP being completed | I62: Only doing 50/50 RCCP: Assumptions are documented regarding Demand / Volume used as inputs for the RCCP volume | J62: Doing both 50/50 & High Side: Assumptions are documented regarding Demand / Volume used as inputs for the RCCP volume Other "what if's" besides High Side are evaluated as needed | K62: RCCP
A63: Production Capacity Management | B63: 12 | C63: Processes | D63: RCCP issues or deviations from Operating strategy are getting discussed & resolved in SNA? | E63: PSC-Chang | H63: RCCP Risks not being discussed in SNA | I63: Capacity related issues or Operating Strategy deviations (service, inventory, etc.) are being discussed in SNA but no clear plan to reduce risks | J63: RCCP risks are talked and clear plan to reduce risks aligned & shared Capacity related issues or Operating Strategy deviations (service, inventory, etc.) are being discussed in SNA including options and an aligned plan to eliminate or resolve capacity risk is completely All parties affected by decision (PSM, Warehouse, Transportation, etc.) are informed Any aligned changes to the plan (Pre-build, sourcing changes, overtime, etc.) should be added to the Planning Systems of Record to let the systems plan accordingly, where applicable | K63: RCCP
A64: Production Capacity Management | B64: 13 | C64: Processes | D64: For Global Supply Chains: Are RCCP’s aggregated across regions for clear view of overall C:D | E64: PSC-Chang | H64: No process in place | I64: Partial process in place for RCCP’s aggregated across regions for clear view of overall C:D | J64: Full process in place (RCCP’s aggregated across regions for clear view of overall C:D) or don't have GSC | K64: RCCP
A65: Production Capacity Management | B65: 14 | C65: Systems | D65: CSNP is using the standard CSP-BW report | E65: PSC-Chang | H65: Not using standard report | I65: No 1 score for this question | J65: Using standard report: APO-DRP BU's: DRP Forecast Flow Validation Report (FFVR) Non APO-DRP BU's: G-CSP-AO-Demand Flow Verification (DFV) report | K65: RCCP
... A85: Supply Chain Orchestration | B85: 19 | C85: Processes | D85: MPS - Is SNP scorecard updated with all MPS measures & correct targets as per IWS Phase and reviewed at least on quarterly basis? | E85: HP/TC/XQ Plant SNP Yantong/Zhelun/Lijun | H85: Scorecard is not always updated with all measures and/or not always reviewed with insufficient gap analysis and action plan | I85: Scorecard is updated with all measures but not always reviewed or with insufficient gap analysis and action plan | J85: Scorecard is updated and reviewed with all measures with gap analysis and action plan | K85: MPS
A86: Supply Chain Orchestration | B86: 20 | C86: Processes | D86: DDS - Are the action plans updated prior the DDS (follow-ups from previous meeting + new known issues added + Actions are updated)? If no current actions because of no issues, check action plan history to confirm action planning is done. | E86: HP/TC/XQ/LY Plant SNP Yantong/Zhelun/Lijun/Xiaoye for D2, PSC Initial/Cookie/Yan for D1/D3/D5/D7 | F86: Action plan has beend documented and tracking completion status. (See screen shot in Column K) | G86: 2 | H86: No action plan exists. | I86: 1 or More Action items exists with due date today or in the past and not resolved yet | J86: All Action Items have dates in the future and are reviewed with the same frequency as the DDS | K86: DDS
A87: Supply Chain Orchestration | B87: 21 | C87: Processes | D87: DDS - Are ALL off-track measures being action planned during the DDS? | E87: HP/TC/XQ/LY Plant SNP Yantong/Zhelun/Lijun/Xiaoye for D2, PSC Initial/Cookie/Yan for D1/D3/D5/D7 | F87: If yesterday service offtrack, we will review 空仓点回补action plan, and focus check production trigger and reflect it into today's production scheduling. If yesterday production have gap will identify mitigation plan, and call out risk if any. | G87: 2 | H87: Off-Track in-process measures not actioned | I87: 50% of off-track in-process measures are actioned | J87: All Off-Track in-process measures are actioned | K87: DDS
A88: Supply Chain Orchestration | B88: 22 | C88: Processes | D88: DDS - Are the mandatory attendees - as per the CBA - the only participants of the meeting? | E88: HP/TC/XQ/LY Plant SNP Yantong/Zhelun/Lijun/Xiaoye for D2, PSC Initial/Cookie/Yan for D1/D3/D5/D7 | F88: In DDS1, we will have plant spoc/MRP/SIP/DRP to review identified triggers and define action plan | G88: 2 | H88: 1 or more Mandatory Attendee are not regularly attending | I88: All mandatory attendees are regularly attending but 1 or More Non-Mandatory Attendee (not regularly) attending the meeting without adding value | J88: Only mandatory attendees are in the meeting, with clear ownership of their respective measures OR 1 or More Non-Mandatory Attendee attending the meeting but clearly adding value. | K88: DDS
A89: Supply Chain Orchestration | B89: 23 | C89: Processes | D89: DDS - Preparation - Are the latest measures actuals completed in the review tool before the meeting? | E89: HP/TC/XQ/LY Plant SNP Yantong/Zhelun/Lijun/Xiaoye for D2, PSC Initial/Cookie/Yan for D1/D3/D5/D7 | F89: we use DDS1 dashboard, so measures will reflect before DDS | G89: 2 | H89: More than 2 measures have no data filled | I89: Maximum of 2 Measures not filled | J89: ALL in-process measures are filled | K89: DDS
A90: Supply Chain Orchestration | B90: 24 | C90: Processes | D90: DDS - Are the Targets & Escalation Triggers documented and known by respective measure owners? Are targets shown in the review tool next to the actual results? | E90: HP/TC/XQ/LY Plant SNP Yantong/Zhelun/Lijun/Xiaoye for D2, PSC Initial/Cookie/Yan for D1/D3/D5/D7 | F90: we use DDS1 dashboard, so target clear show nest to results | G90: 2 | H90: More than 2 Measures have no clear targets or their targets are not shown in the review tool next to the actuals. | I90: Maximum of 2 Measures have no clear targets or their targets are not shown in the review tool next to the actuals. | J90: ALL in-process measures have clear targets and target owners know where the targets are originating from and their targets are not shown in the review tool next to the actuals. | K90: DDS
A91: Supply Chain Orchestration | B91: 25 | C91: Processes | D91: DDS - Does the DDS review ALL and ONLY the standard measures as per the CBA? | E91: HP/TC/XQ/LY Plant SNP Yantong/Zhelun/Lijun/Xiaoye for D2, PSC Initial/Cookie/Yan for D1/D3/D5/D7 | F91: same as above | G91: 2 | H91: Not all Standard Measures as per the CBA are reviewed. | I91: All Standard Measures as per the CBA are reviewed AND DDS discusses NON-Standard measures that have NOT been aligned with the global BU HPN leader AND the HPN RPL | J91: All Standard Measures as per the CBA are reviewed AND (if applicable) DDS discusses NON-Standard measures that have been aligned with the global BU HPN leader AND the HPN RPL - written alignment including rational required. | K91: DDS
A92: Supply Chain Orchestration | B92: 26 | C92: Processes | D92: DDS - Is the DDS frequency as per the CBA [Daily/Weekly/Monthly/Quarterly]? | E92: HP/TC/XQ/LY Plant SNP Yantong/Zhelun/Lijun/Xiaoye for D2, PSC Initial/Cookie/Yan for D1/D3/D5/D7 | F92: DDS1 is daily drumbeat | G92: 2 | H92: DDS Frequency is missed >10% of the times Example: if frequency is Daily, the DDS gets missed 3 Days within 25 WDs in a month | I92: DDS Frequency is missed <10% of the times Example: if frequency is Daily, the DDS gets missed 3 Days within 25 WDs in a month | J92: DDS is happening as per the correct frequency all the time | K92: DDS
A93: Supply Chain Orchestration | B93: 27 | C93: Processes | D93: DDS - Is the DDS taking proper time - No Gap No Yap? | E93: HP/TC/XQ/LY Plant SNP Yantong/Zhelun/Lijun/Xiaoye for D2, PSC Initial/Cookie/Yan for D1/D3/D5/D7 | F93: DDS1 will close within 15~30mins | G93: 2 | H93: DDS timing expands into non-fruitful discussions and doesn't follow the standard time and agenda as per the CBA | I93: DDS timing expands into not-needed discussions but follows the standard time and agenda as per the CBA | J93: DDS time spent ONLY follows the standard time and agenda as per the CBA | K93: DDS
A94: Supply Chain Orchestration | B94: 28 | C94: Processes | D94: POSS - Is POSS available in ePOSS? | E94: HP/TC/XQ Plant SNP Yantong/Zhelun/Lijun | H94: All POSS are not available in E-POSS | I94: 75% of POSS Available in E-POSS | J94: 100% of POSS Available in E-POSS | K94: POSS
A95: Supply Chain Orchestration | B95: 29 | C95: Processes | D95: POSS - POSS is built in line with Site CBN, PSC and BU CBN, OGSM & GTM Ops strategies. Strategies are differentiated via Segmentation and Replenishment Stream (when applicable). Link to E2E Ops strategy available. Site Finance Leader was involved and verified that POSS supports Firm targets delivery. | E95: HP/TC/XQ Plant SNP Yantong/Zhelun/Lijun | H95: Does not include Service-Cash-Cost-Performance Targets | I95: Includes partially Service-Cash-Cost-Performance Targets | J95: Includes all targets Service-Cash-Cost-Performance | K95: POSS
A96: Supply Chain Orchestration | B96: 30 | C96: Processes | D96: POSS - POSS alignment from BU SNO Senior Director happened within the last 12 month at min. | E96: HP/TC/XQ Plant SNP Yantong/Zhelun/Lijun | H96: No POSS updates in any section in the last 12 months | I96: POSS updated but not approved in last 12 months | J96: POSS approved within 12 months | K96: POSS
A97: Supply Chain Orchestration | B97: 31 | C97: Processes | D97: POSS - POSS is known and used by both plant and BU organizations (PSC). (Random check of parameters aligned with plant SPOCs and PSC Planners) | E97: HP/TC/XQ Plant SNP Yantong/Zhelun/Lijun | H97: No audit performed | I97: Audit performed every 12 months | J97: Audit performed every 6 months | K97: POSS
A98: Supply Chain Orchestration | B98: 32 | C98: Processes | D98: POSS - POSS deviations are monitored in the Mfg. Daily DDS (D2), and gap analysis on those deviations are reviewed in Weekly DDS (D6) Scheduling and Results review and PDCA is in place to reduce the number of POSS deviations. | E98: HP/TC/XQ Plant SNP Yantong/Zhelun/Lijun | H98: No POSS deviations review | I98: POSS deviations review on a monthly meeting | J98: POSS deviations review on daily/weekly DDS and monthly meeting | K98: POSS
A99: Supply Chain Orchestration | B99: 33 | C99: Processes | D99: PCL - Are the compliance results of your parameter governance measures reviewed monthly, gap analyzed with action plan identified? | E99: PSC-Yan | H99: No tracking on monthly basis | I99: Tracking done on quarterly basis & no clear action plan | J99: Tracking done on Monthly basis with clear action plan | K99: PCL
A100: Supply Chain Orchestration | B100: 34 | C100: Processes | D100: PCL - Is the monthly/weekly pit-stop and daily DDS in place for both RPI and FP parameter centerline improvement, reflecting the demonstrated capability? | E100: PSC-Yan | H100: No Pit stops are in place to review & gap analyze issues | I100: Pit stops are in place but no gap analysis is shared | J100: Pit stops are in place to review & gap analyze issues | K100: PCL
A101: Supply Chain Orchestration | B101: 35 | C101: Processes | D101: PCL - Is your category leveraging standard parameter center-lining tools to drive parameter center-lining (e.g. MD&CL, IP@100, etc.) | E101: PSC-Yan | H101: NO tracking on monthly basis | I101: Tracking done on monthly basis but score Red | J101: Tracking done on Monthly basis and score green | K101: PCL
A102: Supply Chain Orchestration | B102: 36 | C102: Processes | D102: POW Are your RBU SNO leader and GTM Director enrolled in the E2E Operating Strategy process, and understand the role of POW in the process include its purpose and value? | E102: PSC-Yan | H102: RBU SNO leader and GTM Director are not enrolled in the E2E Operating Strategy process | I102: One of the RBU SNO Leader or GTM Director is enrolled in the E2E Operating Strategy Process | J102: RBU SNO leader and GTM Director are enrolled in the E2E Operating Strategy process | K102: POW
A103: Supply Chain Orchestration | B103: 37 | C103: Processes | D103: POW - Does your RBU have a Category Operating Strategy Choices (Step 9 in the E2E Operating Strategy process) in place with right level of granularity (e.g. by replenishment stream by segment choices are clear), which is renewed annually according to the Business Strategy? | E103: PSC-Yan | H103: RBU doesn't have Category Operating Strategy Choices in place | I103: RBU has Category Operating Strategy Choices in place without right level of granularity | J103: RBU has Category Operating Strategy Choices in place with right level of granularity | K103: POW
A104: Supply Chain Orchestration | B104: 38 | C104: Processes | D104: POW - Has there been a POW completed in the last 12 months (minimum) that follows the POW CBA, with the focus on the changes in the Category Operating Strategy Choices (rather than full parameter landscape loss analysis)? | E104: PSC-Yan | H104: No POW has been completed in the last 12 months | I104: POW has been completed in the last 12 months but not following the POW CBA | J104: POW has been completed in the last 12 months following the POW CBA | K104: POW
A105: Supply Chain Orchestration | B105: 39 | C105: Processes | D105: POW - As an outcome from the POW, does your RBU have an agreed & updated (captured in the planning systems (SAP, OMP+)) set of Parameters(*) for use by the PSC and Plant which feed into the respective POSS (Plant), MOA (Market) and MOS (Materials) agreement documents for setting up in the planning systems? * prioritize the critical 10 parameters | E105: PSC-Yan | H105: No or <75% of parameters agreed & updated | I105: 75% of parameters agreed & updated (7 parameters out of 10 updated) | J105: 100% of parameters agreed & updated | K105: POW
... A117: Supply Chain Orchestration | B117: 51 | C117: Systems | D117: MPS - Is master data updated by System Owner & following MPS standard? | E117: HP/TC/XQ/LY Plant SNP Yantong/Zhelun/Lijun/Xiaoye | H117: SAP is not fully updated with right master and update is not managed by System Owner | I117: SAP is not fully updated with right master data but update is managed by System Owner | J117: SAP is updated with right master data following MPS Standard & updated by System Owner | K117: MPS
A118: Supply Chain Orchestration | B118: 52 | C118: Systems | D118: DDS - Are the measures reviewed & action planning done using the standard tool? [DDS-i OR a locally developed dashboard, only if aligned with respective HPN RPL for the region] | E118: HP/TC/XQ/LY Plant SNP Yantong/Zhelun/Lijun/Xiaoye for D2, PSC Initial/Cookie/Yan for D1/D3/D5/D7 | F118: All measures are reviewed via standard Dashboard, and action plan we are using excel to document. | G118: 1 | H118: DDS Reviewed & action planning done through non standard tool not aligned with HPN RPL | I118: DDS reviewed using standard tool or aligned tool with HPN RPL but action planning done using non standard tool or tool not aligned with HPN RPL or vice versa - proof of alignment required | J118: DDS reviewed & action planning done though standard tool or aligned tool with HPN RPL - proof of alignment required
A119: Supply Chain Orchestration | B119: 53 | C119: Systems | D119: Is the E2E Parameter Centerline tool leveraged to support the execution of operating strategy execution, include planning orchestration workshop preparation, execution, and ongoing governance to enable identification of losses/opportunities? | E119: PSC-Yan | H119: No workshop done | I119: Workshop done with no clear action plan | J119: Workshop done with clear action plan using E2E PCL tool | K119: PCL

Sheet 2Y # of  Qs compare (2)
A2: # of Questions Compare
B3: Results | D3: Capability | F3: Processes | H3: Systems | J3: Total
A4: Work Process Assessment | B4: FY2526 | C4: FY2425 | D4: FY2526 | E4: FY2425 | F4: FY2526 | G4: FY2425 | H4: FY2526 | I4: FY2425 | J4: FY2526 | K4: FY2425
A5: Integrated Inventory Management | B5: 2 | C5: 3 | D5: 5 | E5: 6 | F5: 21 | G5: 21 | H5: 8 | I5: 8 | J5: =SUM(B5,D5,F5,H5) -> 36 | K5: =SUM(C5,E5,G5,I5) -> 38
A6: Integrated Service | B6: 1 | C6: 1 | D6: 4 | E6: 4 | F6: 6 | G6: 6 | H6: 1 | I6: 1 | J6: =SUM(B6,D6,F6,H6) -> 12 | K6: =SUM(C6,E6,G6,I6) -> 12
A7: Production Capacity | B7: 2 | C7: 2 | D7: 3 | E7: 3 | F7: 8 | G7: 8 | H7: 2 | I7: 2 | J7: =SUM(B7,D7,F7,H7) -> 15 | K7: =SUM(C7,E7,G7,I7) -> 15
A8: Supply Chain Orchestration | B8: 2 | C8: 2 | D8: 10 | E8: 10 | F8: 31 | G8: 37 | H8: 4 | I8: 4 | J8: =SUM(B8,D8,F8,H8) -> 47 | K8: =SUM(C8,E8,G8,I8) -> 53
B9: =SUM(B5:B8) -> 7 | C9: =SUM(C5:C8) -> 8 | D9: =SUM(D5:D8) -> 22 | E9: =SUM(E5:E8) -> 23 | F9: =SUM(F5:F8) -> 66 | G9: =SUM(G5:G8) -> 72 | H9: =SUM(H5:H8) -> 15 | I9: =SUM(I5:I8) -> 15 | J9: =SUM(B9,D9,F9,H9) -> 110 | K9: =SUM(C9,E9,G9,I9) -> 118
A11: Highlights changes: | B11: 1. Integrated Inv. management, 3 QS reduced, 1 is from result- situational safety tracking cancelled. 2 Qs. cancelled from process- NPI physically exceed 180 days, UPI discussed in D12. QS NPI qs. >90 evaluation and execution being reviewd and quarterly accural qs. split to 2 qs.
B12: 2. Supply chain Orchestration- Cancel 1 QS- POSS, 2 QS-PCL, 2 QS-POW, 1 QS- MSAnT . MSAnT name changes to Manufacturing agility workshop.

Sheet Integrated Inv. comp.
A1: FY2526 | B1: Section | C1: Question | D1: difference | E1: owner | G1: FY2425 | H1: Section | I1: Question | K1: owner
B2: Results | C2: ITS-FP & RPM: Situational Safety less than or equal 2% average FYTD or as per BU aligned glidepaths ? | D2: 删除 | E2: - | G2: 1 | H2: Results | I2: ITS-FP & RPM: Situational Safety less than or equal 2% average FYTD or as per BU aligned glidepaths ? | J2: FY2425 | K2: PSC-Sophia
A3: 1 | B3: Results | C3: IM- UPI: Total (FP + RPI) % UPI FYTD and Glide path (remainder of the FY) is on or below BU target for the current FY | D3: same | E3: =VLOOKUP(C:C,'FY2526 Questions & Owners-All '!E:F,2,FALSE) -> PSC-Sophia | G3: 2 | H3: Results | I3: IM- UPI: % UPI and Glide path (remainder of the FY) is on or below BU target for the current FY | J3: FY2425 | K3: PSC-Sophia
A4: 2 | B4: Results | C4: IM: Is the evaluation for NPI is performed within 90 days of NPI is identified? Is the action plan for disposal or depletion of NPI physically executed within 90 days after evaluated? | D4: same | E4: =VLOOKUP(C:C,'FY2526 Questions & Owners-All '!E:F,2,FALSE) -> PSC-Yuchen | G4: 3 | H4: Results | I4: IM: Is the evaluation for NPI is performed within 90 days of NPI is identified? Is the action plan for disposal or depletion of NPI physically executed within 90 days after evaluated? | J4: FY2425 | K4: PSC-Yuchen
A5: 3 | B5: Capability | C5: ITS – FP: ITS Users are able to run scenarios to investigate impacts of supply chain changes or parameter changes into Safety calculations | D5: same | E5: =VLOOKUP(C:C,'FY2526 Questions & Owners-All '!E:F,2,FALSE) -> PSC-Sophia | G5: 4 | H5: Capability | I5: ITS – FP: ITS Users are able to run scenarios to investigate impacts of supply chain changes or parameter changes into Safety calculations | J5: FY2425 | K5: PSC-Ann
A6: 4 | B6: Capability | C6: ITS – FP& RPM : Are all KU or/and system owners qualified within 6 months from starting role? | D6: same | E6: =VLOOKUP(C:C,'FY2526 Questions & Owners-All '!E:F,2,FALSE) -> PSC-Sophia for FP, Jiawen for RPM | G6: 5 | H6: Capability | I6: ITS – FP& RPM : Are all KU or/and system owners qualified within 6 months from starting role? | J6: FY2425 | K6: PSC-Ann for FP, Jiawen for RM
A7: 5 | B7: Capability | C7: IM- Leadership: Are the Regional inventory solutions Key Users in place and qualified by Regional BPX via the Step Up Card? | D7: same | E7: =VLOOKUP(C:C,'FY2526 Questions & Owners-All '!E:F,2,FALSE) -> PSC-Sophia | G7: 6 | H7: Capability | I7: IM- Leadership: Are the Regional inventory solutions Key Users in place and qualified by Regional BPX via the Step Up Card? | J7: FY2425 | K7: PSC-Sophia
A8: 6 | B8: Capability | C8: Cash RCLA: Is there a Loss Analysis Leader identified for the RBU and is qualified on RCLA Step Up Card ? | D8: same | E8: =VLOOKUP(C:C,'FY2526 Questions & Owners-All '!E:F,2,FALSE) -> PSC-Sophia | G8: 7 | H8: Capability | I8: Cash RCLA: Is there a Loss Analysis Leader identified for the RBU and is qualified on RCLA Step Up Card ? | J8: FY2425 | K8: PSC-Sophia
A9: 7 | B9: Capability | C9: Process owner defined for every work process and ensures in process/out process measures are tracked & visible (FP ITS, RPM ITS, Cash RCLA & IM) | D9: 改动过 | E9: =VLOOKUP(C:C,'FY2526 Questions & Owners-All '!E:F,2,FALSE) -> PSC-Suz. | G9: 8 | H9: Capability | I9: Process owner defined for every work process and ensures in process/out process measures are tracked & visible | J9: FY2425 | K9: PSC-Yan
B10: Capability | C10: IM - UPI:Is there any physical NPI exceeding 180 days ? Is exception granted from B4 F&A ? | D10: 删除 | E10: - | G10: 9 | H10: Capability | I10: IM - UPI:Is there any physical NPI exceeding 180 days ? Is exception granted from B4 F&A ? | J10: FY2425 | K10: PSC-Yuchen
A11: 8 | B11: Processes | C11: ITS – FP: Was standard PACE model and SWP followed throughout the process? | D11: same | E11: =VLOOKUP(C:C,'FY2526 Questions & Owners-All '!E:F,2,FALSE) -> PSC-Sophia | G11: 10 | H11: Processes | I11: ITS – FP: Was standard PACE model and SWP followed throughout the process? | J11: FY2425 | K11: PSC-Ann
A12: 9 | B12: Processes | C12: ITS FP: Is master data in ITS tool correct and verified on weekly basis, including parameters coming from ITS operating strategy | D12: same | E12: =VLOOKUP(C:C,'FY2526 Questions & Owners-All '!E:F,2,FALSE) -> PSC-Sophia | G12: 11 | H12: Processes | I12: ITS FP: Is master data in ITS tool correct and verified on weekly basis, including parameters coming from ITS operating strategy | J12: FY2425 | K12: PSC-Ann
A13: 10 | B13: Processes | C13: ITS – FP: Are you reviewing SS from all location/code combinations for all Codes that carrying safety is required (Sites that are stocking locations) | D13: same | E13: =VLOOKUP(C:C,'FY2526 Questions & Owners-All '!E:F,2,FALSE) -> PSC-Sophia | G13: 12 | H13: Processes | I13: ITS – FP: Are you reviewing SS from all location/code combinations for all Codes that carrying safety is required (Sites that are stocking locations) | J13: FY2425 | K13: PSC-Ann
A14: 11 | B14: Processes | C14: ITS – FP: Do you have an up to date ITS Operating Strategy as per CBA (including exception handling), to communicate critical inventory target setting parameters supporting different business cases and supply chains. | D14: same | E14: =VLOOKUP(C:C,'FY2526 Questions & Owners-All '!E:F,2,FALSE) -> PSC-Sophia | G14: 13 | H14: Processes | I14: ITS – FP: Do you have an up to date ITS Operating Strategy as per CBA (including exception handling), to communicate critical inventory target setting parameters supporting different business cases and supply chains. | J14: FY2425 | K14: PSC-Ann
A15: 12 | B15: Processes | C15: ITS – FP: Were identified safety concerns troubleshot to root cause and addressed in a timely manner? | D15: same | E15: =VLOOKUP(C:C,'FY2526 Questions & Owners-All '!E:F,2,FALSE) -> PSC-Sophia | G15: 14 | H15: Processes | I15: ITS – FP: Were identified safety concerns troubleshot to root cause and addressed in a timely manner? | J15: FY2425 | K15: PSC-Ann
A16: 13 | B16: Processes | C16: ITS-RPM:Is ITS RPM review conducted on monthly basis for all supply chains ? "Quarterly If aligned" | D16: same | E16: =VLOOKUP(C:C,'FY2526 Questions & Owners-All '!E:F,2,FALSE) -> PSC-Jiawen | G16: 15 | H16: Processes | I16: ITS-RPM:Is ITS RPM review conducted on monthly basis for all supply chains ? "Quarterly If aligned" | J16: FY2425 | K16: PSC-Jiawen
A17: 14 | B17: Processes | C17: ITS-RPM: Is agreed SSS aligned with the supply chain leader before upload? | D17: same | E17: =VLOOKUP(C:C,'FY2526 Questions & Owners-All '!E:F,2,FALSE) -> PSC-Jiawen | G17: 16 | H17: Processes | I17: ITS-RPM: Is agreed SSS aligned with the supply chain leader before upload? | J17: FY2425 | K17: PSC-Jiawen
A18: 15 | B18: Processes | C18: Cash RCLA: Is CASH RCLA SWP being applied in BU and the loss analysis occurred during last 12 months to feed following FY Inventory FIRM ? | D18: same | E18: =VLOOKUP(C:C,'FY2526 Questions & Owners-All '!E:F,2,FALSE) -> PSC-Sophia | G18: 17 | H18: Processes | I18: Cash RCLA: Is CASH RCLA SWP being applied in BU and the loss analysis occurred during last 12 months to feed following FY Inventory FIRM ? | J18: FY2425 | K18: PSC-Sophia
A19: 16 | B19: Processes | C19: Cash RCLA:Is there a regular PDCA cycle that includes the measures & actions tracking ? Are the losses eliminated as per plan ? | D19: same | E19: =VLOOKUP(C:C,'FY2526 Questions & Owners-All '!E:F,2,FALSE) -> PSC-Sophia | G19: 18 | H19: Processes | I19: Cash RCLA:Is there a regular PDCA cycle that includes the measures & actions tracking ? Are the losses eliminated as per plan ? | J19: FY2425 | K19: PSC-Sophia
A20: 17 | B20: Processes | C20: Cash RCLA: Are there clear Cash DOH or FCF targets for the next 3 years ahead of RCLA deployed by leadership ? | D20: 改动过 | E20: =VLOOKUP(C:C,'FY2526 Questions & Owners-All '!E:F,2,FALSE) -> PSC-Sophia | G20: 19 | H20: Processes | I20: Cash RCLA: Are there clear Cash DOH targets for the next 3 years ahead of RCLA deployed by leadership ? | J20: FY2425 | K20: PSC-Sophia
A21: 18 | B21: Processes | C21: Cash RCLA: Are the loss elimination opportunities (TAPA) sufficient to meet the business requirements? | D21: same | E21: =VLOOKUP(C:C,'FY2526 Questions & Owners-All '!E:F,2,FALSE) -> PSC-Sophia | G21: 20 | H21: Processes | I21: Cash RCLA: Are the loss elimination opportunities (TAPA) sufficient to meet the business requirements? | J21: FY2425 | K21: PSC-Sophia
A22: 19 | B22: Processes | C22: IM- UPI :Is the VS / Category tracking UPI at the bucket level on a weekly basis and communicating internally and to RBU, PSC and SMO leadership on a monthly basis, including leadership reviews? Are the defined and agreed actions sufficient to prevent the inventory gaps from reoccurring? | D22: same | E22: PSC-Sophia | G22: 21 | H22: Processes | I22: IM- UPI :Is the VS / Category tracking UPI at the bucket level on a weekly basis and communicating internally and to RBU, PSC and SMO leadership on a monthly basis, including leadership reviews? Are the defined and agreed actions sufficient to prevent the inventory gaps from reoccurring? | J22: FY2425 | K22: PSC-Sophia
A23: 20 | B23: Processes | C23: IM- UPI: Are NPI codes >90d in Evaluation and Execution being reviewed on a weekly basis and prioritized for action planning. | D23: 改动过 | E23: =VLOOKUP(C:C,'FY2526 Questions & Owners-All '!E:F,2,FALSE) -> PSC-Yuchen | G23: 22 | H23: Processes | I23: IM- UPI: Are NPI codes >90d in Decision and Execution "Decision Phase" being reviewed on a weekly basis and prioritized for action planning. Is the NPI Accrual SWP being followed each Quarter? | J23: FY2425 | K23: PSC-Yuchen
A24: 21 | B24: Processes | C24: IM-UPI: Is NPI accrual done on quarterly basis following the accruals SWP | D24: 拆分出来单独一个问题 | E24: =VLOOKUP(C:C,'FY2526 Questions & Owners-All '!E:F,2,FALSE) -> PSC-Yuchen
A25: 22 | B25: Processes | C25: IM: Does the VS / Category have scheduled active reviews within the category, RBU and sites to discuss inventory/ UPI issues( Gap versus glidepath) on a weekly basis (weekly Category DDS)? AND on a monthly basis to discuss inv/ UPI issues ( Gap versus glidepath), obstacles and action plans (SNA )? | D25: same | E25: PSC-Sophia | G25: 23 | H25: Processes | I25: IM-OS: Does the VS / Category have scheduled active reviews within the category, RBU and sites to discuss inventory/ UPI issues( Gap versus glidepath) on a weekly basis (weekly Category DDS)? AND on a monthly basis to discuss inv/ UPI issues ( Gap versus glidepath), obstacles and action plans (SNA )? | J25: FY2425 | K25: PSC-Sophia
A26: 23 | B26: Processes | C26: IM: Are the Daily/Weekly VS (Value Stream), Category, and Demand/Supply DDS covering Inventory/UPI? | D26: 改动过 | E26: =VLOOKUP(C:C,'FY2526 Questions & Owners-All '!E:F,2,FALSE) -> PSC-Sophia | G26: 24 | H26: Processes | I26: IM- RTT: Are the Daily/Weekly VS (Value Stream), Category, and Demand/Supply DDS covering Inventory? | J26: FY2425 | K26: PSC-Sophia
A27: 24 | B27: Processes | C27: IM: Is inventory FF is conducted on monthly basis with clear targets for FP & RPM month closure ? | D27: same | E27: =VLOOKUP(C:C,'FY2526 Questions & Owners-All '!E:F,2,FALSE) -> PSC-Sophia | G27: 25 | H27: Processes | I27: IM- target: Is inventory FF is conducted on monthly basis with clear targets for FP & RPM month closure ? | J27: FY2425 | K27: PSC-Sophia
A28: 25 | B28: Processes | C28: IM- Initiatives: Is the VS / Category executing the PIPO DMS as required for all their initiatives? | D28: same | E28: =VLOOKUP(C:C,'FY2526 Questions & Owners-All '!E:F,2,FALSE) -> PSC-Sophia | G28: 26 | H28: Processes | I28: IM- Initiatives: Is the VS / Category executing the PIPO DMS as required for all their initiatives? | J28: FY2425 | K28: PSC-Sophia
A29: 26 | B29: Processes | C29: IM- Initiative: Has the VS / Category documented Anticipation Inventory assumptions into Operating Strategy and executing it ? | D29: same | E29: =VLOOKUP(C:C,'FY2526 Questions & Owners-All '!E:F,2,FALSE) -> PSC-Sophia | G29: 27 | H29: Processes | I29: IM- Initiative: Has the VS / Category documented Anticipation Inventory assumptions into Operating Strategy and executing it ? | J29: FY2425 | K29: PSC-Sophia
A30: 27 | B30: Processes | C30: IM- Initiatives: Does the VS / Category have a robust process to ensure quarterly initiative reviews to reflect as building blocks to the inventory glidepath as part of the Master Plan review and are the building blocks properly communicated and incorporated into the glidepath? | D30: same | E30: PSC-Sophia | G30: 28 | H30: Processes | I30: IM- Initiatives: Does the VS / Category have a robust process to ensure quarterly initiative reviews to reflect as building blocks to the inventory glidepath as part of the Master Plan review and are the building blocks properly communicated and incorporated into the glidepath? | J30: FY2425 | K30: PSC-Sophia
A31: 28 | B31: Processes | C31: IM- RTT: (IWL) FYTD on track or as per OU aligned glidepaths ? Is action plan set for codes exceeding limits ? | D31: same | E31: =VLOOKUP(C:C,'FY2526 Questions & Owners-All '!E:F,2,FALSE) -> PSC-Suz. | G31: 29 | H31: Processes | I31: IM- RTT: (IWL) FYTD on track or as per OU aligned glidepaths ? Is action plan set for codes exceeding limits ? | J31: FY2425 | K31: PSC-Yan
B32: Processes | C32: IM- Demand: Is UPI behind demand discussed in D12 ( Demand WTP) ? | D32: 删除 | E32: - | G32: 30 | H32: Processes | I32: IM- Demand: Is UPI behind demand discussed in D12 ( Demand WTP) ? | J32: FY2425 | K32: PSC-Sophia
A33: 29 | B33: Systems | C33: ITS – FP: Is Standard ITS tool used for calculating and writing back safety (and max stock) settings for finished products ( A-ITS in NA, rest IBPI) | D33: same | E33: =VLOOKUP(C:C,'FY2526 Questions & Owners-All '!E:F,2,FALSE) -> PSC-Sophia | G33: 31 | H33: Systems | I33: ITS – FP: Is Standard ITS tool used for calculating and writing back safety (and max stock) settings for finished products ( A-ITS in NA, rest IBPI) | J33: FY2425 | K33: PSC-Ann
A34: 30 | B34: Systems | C34: ITS – FP: Are you adhering to ITS tools recommendations? Are action plans in place to improve? | D34: 改动过 | E34: =VLOOKUP(C:C,'FY2526 Questions & Owners-All '!E:F,2,FALSE) -> PSC-Sophia | G34: 32 | H34: Systems | I34: ITS – FP: There is healthy level of statistical/strategic safety as communicated in process measures? Or were action plans set in place as needed to improve in-process and output measures? | J34: FY2425 | K34: PSC-Ann
A35: 31 | B35: Systems | C35: ITS-RPM: Is the standard parameter matrix file is updated for 100% of the sites of your BU? (excluding Contract manufacturing as it's not P&G owned ) | D35: same | E35: =VLOOKUP(C:C,'FY2526 Questions & Owners-All '!E:F,2,FALSE) -> PSC-Jiawen | G35: 33 | H35: Systems | I35: ITS-RPM: Is the standard parameter matrix file is updated for 100% of the sites of your BU? (excluding Contract manufacturing as it's not P&G owned ) | J35: FY2425 | K35: PSC-Jiawen
A36: 32 | B36: Systems | C36: ITS-RPM: Is the writeback% is 90% or more ? | D36: same | E36: =VLOOKUP(C:C,'FY2526 Questions & Owners-All '!E:F,2,FALSE) -> PSC-Jiawen | G36: 34 | H36: Systems | I36: ITS-RPM: Is the writeback% is 90% or more ? | J36: FY2425 | K36: PSC-Jiawen
A37: 33 | B37: Systems | C37: ITS-RPM: Are 80% of the aligned SS within tolerance of SS recommendation? (+/- 20%) [if SS is exceeding tolerance, please add reason in a comment] | D37: same | E37: =VLOOKUP(C:C,'FY2526 Questions & Owners-All '!E:F,2,FALSE) -> PSC-Jiawen | G37: 35 | H37: Systems | I37: ITS-RPM: Are 80% of the aligned SS within tolerance of SS recommendation? (+/- 20%) [if SS is exceeding tolerance, please add reason in a comment] | J37: FY2425 | K37: PSC-Jiawen
A38: 34 | B38: Systems | C38: Cash RCLA: Is Cash RCLA and Ideal state calculator standard tools used to run the analysis and define losses ? | D38: same | E38: =VLOOKUP(C:C,'FY2526 Questions & Owners-All '!E:F,2,FALSE) -> PSC-Sophia | G38: 36 | H38: Systems | I38: Cash RCLA: Is Cash RCLA and Ideal state calculator standard tools used to run the analysis and define losses ? | J38: FY2425 | K38: PSC-Sophia
A39: 35 | B39: Systems | C39: IM- UPI: Is UPI portal used for UPI actioning ? | D39: same | E39: =VLOOKUP(C:C,'FY2526 Questions & Owners-All '!E:F,2,FALSE) -> PSC-Sophia | G39: 37 | H39: Systems | I39: IM- UPI: Is UPI portal used for UPI actioning ? | J39: FY2425 | K39: PSC-Sophia
A40: 36 | B40: Systems | C40: IM- UPI: Is the VS / Category executing in depth analysis of top issues utilizing HIT graphs (ISC PBI) at least quarterly for FP and RPI ? | D40: same | E40: =VLOOKUP(C:C,'FY2526 Questions & Owners-All '!E:F,2,FALSE) -> PSC-Sophia | G40: 38 | H40: Systems | I40: IM- UPI: Is the VS / Category executing in depth analysis of top issues utilizing HIT graphs (ISC PBI) at least quarterly for FP and RPI ? | J40: FY2425 | K40: PSC-Sophia

Sheet Integrated Service comp.
A1: FY2526 | B1: Section | C1: Question | D1: difference | E1: owner | G1: No | H1: Section | I1: Question | K1: owner
A2: 1 | B2: Results | C2: Unanalyzed cuts (Cuts root caused 7.1.1) are < 5% for at least 9 months out of the last 12 months | D2: same | E2: PSC-Yuchen | G2: 1 | H2: Results | I2: Unanalyzed cuts (Cuts root caused 7.1.1) are < 5% for at least 9 months out of the last 12 months | J2: FY2425 | K2: =VLOOKUP(I:I,'[5]FY2425 CSNP HC Question & Owner'!$D:$E,2,FALSE) -> PSC-Ann
A3: 2 | B3: Capability | C3: Are the Regional TOF Key Users in place? | D3: same | E3: PSC-Cookie | G3: 2 | H3: Capability | I3: Are the Regional TOF Key Users in place? | J3: FY2425 | K3: =VLOOKUP(I:I,'[5]FY2425 CSNP HC Question & Owner'!$D:$E,2,FALSE) -> PSC-Cookie
A4: 3 | B4: Capability | C4: Is the TOF Key User knowledge sufficient to help the Organization leverage service tools to drive appropriate action plans and insights? | D4: same | E4: PSC-Cookie | G4: 3 | H4: Capability | I4: Is the TOF Key User knowledge sufficient to help the Organization leverage service tools to drive appropriate action plans and insights? | J4: FY2425 | K4: =VLOOKUP(I:I,'[5]FY2425 CSNP HC Question & Owner'!$D:$E,2,FALSE) -> PSC-Cookie
A5: 4 | B5: Capability | C5: Are the Leaders validating the proper use of Root Causes? And intervening where needed to address and remove the main TOF Root Causes? (For Example: Which system or Work Process failed ? Are Leaders assessing the plausibility of the proposed actions ? Are the defined and agreed actions sufficient to prevent the TOF from reoccurring?) | D5: same | E5: PSC-Cookie | G5: 4 | H5: Capability | I5: Are the Leaders validating the proper use of Root Causes? And intervening where needed to address and remove the main TOF Root Causes? (For Example: Which system or Work Process failed ? Are Leaders assessing the plausibility of the proposed actions ? Are the defined and agreed actions sufficient to prevent the TOF from reoccurring?) | J5: FY2425 | K5: PSC-Cookie
A6: 5 | B6: Capability | C6: Process owner defined for every work process and ensures in process/out process measures are tracked & visible (Service Management) | D6: 有改动 | E6: PSC-Suz. | G6: 5 | H6: Capability | I6: Process owner defined for every work process and ensures in process/out process measures are tracked & visible | J6: FY2425 | K6: =VLOOKUP(I:I,'[5]FY2425 CSNP HC Question & Owner'!$D:$E,2,FALSE) -> PSC-Yan
A7: 6 | B7: Processes | C7: Does our Codes @ risk process happens at least once/week , covers all gaps within Supply Chain Lead time and mitigation plans are in place? | D7: same | E7: PSC-Yuchen | G7: 6 | H7: Processes | I7: Does our Codes @ risk process happens at least once/week , covers all gaps within Supply Chain Lead time and mitigation plans are in place? | J7: FY2425 | K7: =VLOOKUP(I:I,'[5]FY2425 CSNP HC Question & Owner'!$D:$E,2,FALSE) -> PSC-Ann
A8: 7 | B8: Processes | C8: Is critical Code List (FPCs with gaps against orders in coming 2-3 days) being shared & actioned 100% or as per market defined threshold on daily basis? | D8: same | E8: PSC-Yuchen | G8: 7 | H8: Processes | I8: Is critical Code List (FPCs with gaps against orders in coming 2-3 days) being shared & actioned 100% or as per market defined threshold on daily basis? | J8: FY2425 | K8: =VLOOKUP(I:I,'[5]FY2425 CSNP HC Question & Owner'!$D:$E,2,FALSE) -> PSC-Ann
A9: 8 | B9: Processes | C9: Does the OU has defined PACE for escalation, escalation threshold agreed and action plans triggered after escalation | D9: same | E9: PSC-Yuchen | G9: 8 | H9: Processes | I9: Does the OU has defined PACE for escalation, escalation threshold agreed and action plans triggered after escalation | J9: FY2425 | K9: =VLOOKUP(I:I,'[5]FY2425 CSNP HC Question & Owner'!$D:$E,2,FALSE) -> PSC-Ann
A10: 9 | B10: Processes | C10: Are the TOF weekly or monthly action plans documented, reviewed, and made available to all parties/posted online with link to document? | D10: same | E10: PSC-Cookie | G10: 9 | H10: Processes | I10: Are the TOF weekly or monthly action plans documented, reviewed, and made available to all parties/posted online with link to document? | J10: FY2425 | K10: =VLOOKUP(I:I,'[5]FY2425 CSNP HC Question & Owner'!$D:$E,2,FALSE) -> PSC-Cookie
A11: 10 | B11: Processes | C11: Are the regional hypercare guidelines and triggers being applied and used consistently? | D11: same | E11: PSC-Yuchen | G11: 10 | H11: Processes | I11: Are the regional hypercare guidelines and triggers being applied and used consistently? | J11: FY2425 | K11: =VLOOKUP(I:I,'[5]FY2425 CSNP HC Question & Owner'!$D:$E,2,FALSE) -> PSC-Ann
A12: 11 | B12: Processes | C12: Are exceptions (restatements) and exclusions to TOF results being done using the PACE model as outlined in the TOF CBA? | D12: same | E12: PSC-Cookie | G12: 11 | H12: Processes | I12: Are exceptions (restatements) and exclusions to TOF results being done using the PACE model as outlined in the TOF CBA? | J12: FY2425 | K12: =VLOOKUP(I:I,'[5]FY2425 CSNP HC Question & Owner'!$D:$E,2,FALSE) -> PSC-Ann
A13: 12 | B13: Systems | C13: Do you use standard global reporting tool or regional aligned tool for tracking & rootcausing TOF? | D13: 有改动 有没有用global/regional standard tool vs. 有没有tool | E13: PSC-Cookie | G13: 12 | H13: Systems | I13: Does the TOF data systems /Visualization Tools (TOF, Replenishment/SPACED), Root Cause Tool, Analytics etc.) provide sufficient information to formulate action plans to recover TOF to target ? | J13: FY2425 | K13: =VLOOKUP(I:I,'[5]FY2425 CSNP HC Question & Owner'!$D:$E,2,FALSE) -> PSC-Cookie

Sheet production capacity comp.
A1: FY2526 | B1: Section | C1: Question | D1: difference | E1: Owner | G1: FY2425 | H1: Section | I1: Question | K1: owner
A2: 1 | B2: Results | C2: DFV - Is % difference FYTD average between BW demand hub and planning system < 2% over 18 Months ? | D2: same | E2: PSC-Huarong | G2: 1 | H2: Results | I2: DFV - Is % difference between BW demand hub and planning system < 2% over 18 Months? | J2: FY2425 | K2: PSC-Ann
A3: 2 | B3: Results | C3: ALL except NA: Production C:D compliance above 90% for the next 18 months for all the resources identified as critical NA only: No RCCP resources identified as critical with 1) 2 or more months with CtD < 1.0 or 2) More than 10% of total production requirements volume is below CtD target (Months 2-17, for both Balanced 50/50 and High Side scenarios) | D3: same | E3: PSC-Initial | G3: 2 | H3: Results | I3: Production C:D compliance above 90% for the next 18 months for all the resources identified as critical | J3: FY2425 | K3: PSC-Initial
A4: 3 | B4: Capability | C4: Do all Supply Chains have an identified DFV owner in place and fully trained? | D4: same | E4: PSC- Suz. | G4: 3 | H4: Capability | I4: Do all Supply Chains have an identified DFV owner in place and fully trained? | J4: FY2425 | K4: PSC-Yan
A5: 4 | B5: Capability | C5: Do all RCCP families have an identified RCCP owner in place & fully trained? | D5: same | E5: PSC- Suz. | G5: 4 | H5: Capability | I5: Do all RCCP families have an identified RCCP owner in place & fully trained? | J5: FY2425 | K5: PSC-Yan
A6: 5 | B6: Capability | C6: Process owner defined for every work process and ensures in process/out process measures are tracked & visible (RCCP & DFV) | D6: 有改动 | E6: PSC- Suz. | G6: 5 | H6: Capability | I6: Process owner defined for every work process and ensures in process/out process measures are tracked & visible | J6: FY2425 | K6: PSC-Yan
A7: 6 | B7: Processes | C7: DFV SWP being followed according to the PMC | D7: same | E7: PSC-Huarong | G7: 6 | H7: Processes | I7: DFV SWP being followed according to the PMC | J7: FY2425 | K7: PSC-Ann
A8: 7 | B8: Processes | C8: If you have Global Supply Chains (GSC): Is DFV process in place? | D8: same | E8: PSC-Huarong | G8: 7 | H8: Processes | I8: If you have Global Supply Chains (GSC): Is DFV process in place? | J8: FY2425 | K8: PSC-Ann
A9: 8 | B9: Processes | C9: RCCP SWP being followed according to the RCCP PMC | D9: same | E9: PSC-Chang | G9: 8 | H9: Processes | I9: RCCP SWP being followed according to the RCCP PMC | J9: FY2425 | K9: PSC-Chang
A10: 9 | B10: Processes | C10: RCCP data inputs are coming from the source system | D10: same | E10: PSC-Chang | G10: 9 | H10: Processes | I10: RCCP data inputs are coming from the source system | J10: FY2425 | K10: PSC-Chang
A11: 10 | B11: Processes | C11: Identification of recommended C:D targets is complete | D11: same | E11: PSC-Chang | G11: 10 | H11: Processes | I11: Identification of recommended C:D targets is complete | J11: FY2425 | K11: PSC-Chang
A12: 11 | B12: Processes | C12: Is there a 50/50 & High Side forecast scenario done for all RCCP Families each month? | D12: same | E12: PSC-Chang | G12: 11 | H12: Processes | I12: Is there a 50/50 & High Side forecast scenario done for all RCCP Families each month? | J12: FY2425 | K12: PSC-Chang
A13: 12 | B13: Processes | C13: RCCP issues or deviations from Operating strategy are getting discussed & resolved in SNA? | D13: same | E13: PSC-Chang | G13: 12 | H13: Processes | I13: RCCP issues or deviations from Operating strategy are getting discussed & resolved in SNA? | J13: FY2425 | K13: PSC-Chang
... A16: 15 | B16: Systems | C16: CSNP is using an aligned RCCP solution | D16: same | E16: PSC-Chang | G16: 15 | H16: Systems | I16: CSNP is using an aligned to RCCP solution | J16: FY2425 | K16: PSC-Chang

Sheet supply chain Orches comp.
A1: FY2526 | B1: Section | C1: Question | D1: difference | E1: Owner | G1: FY2425 | H1: Section | I1: Question | J1: Year | K1: owner
A2: 1 | B2: Results | C2: 2 of supply chain nodes DBNX gaps are improving vs. YA or meeting RBU glide path: DNBD vs. DBNC, DBNR vs. DBNS (or DBNO), DBNI vs. DBNO DC. | D2: same | E2: =VLOOKUP(C:C,'FY2526 Questions & Owners-All '!E:F,2,FALSE) -> HP/TC/XQ Plant SNP Ziwei/Jason/Matt | G2: 1 | H2: Results | I2: 2 of supply chain nodes DBNX gaps are improving vs. YA or meeting RBU glide path: DNBD vs. DBNC, DBNR vs. DBNS (or DBNO), DBNI vs. DBNO DC. | J2: FY2425 | K2: HP/TC/XQ Plant SNP Yantong/Zhelun/Lijun
A3: 2 | B3: Results | C3: MPS - Is MPS Output measure consistently being tracked as per PMC and delivered vs sites IWS phase targets? | D3: same | E3: =VLOOKUP(C:C,'FY2526 Questions & Owners-All '!E:F,2,FALSE) -> HP/TC/XQ Plant SNP Ziwei/Jason/Matt | G3: 2 | H3: Results | I3: MPS - Is MPS Output measure consistently being tracked as per PMC and delivered vs sites IWS phase targets? | J3: FY2425 | K3: HP/TC/XQ Plant SNP Yantong/Zhelun/Lijun
A4: 3 | B4: Capability | C4: Staffing - Are all PSC Category CNL/CNA/CSNP Leader, and Manf. Site SNO/SNP Leader(s) Roles filled? | D4: same | E4: =VLOOKUP(C:C,'FY2526 Questions & Owners-All '!E:F,2,FALSE) -> HP/TC/XQ Plant SNP Ziwei/Jason/Matt & PSC Suz. | G4: 3 | H4: Capability | I4: Staffing - Are all PSC Category CNL/CNA/CSNP Leader, and Manuf. Site SNO/SNP Leader(s) Roles filled? | J4: FY2425 | K4: PSC-Yan
A5: 4 | B5: Capability | C5: CNL/CNA/CSNP Resources Qualification is a Priority to ensure business continuity especially during transitions | D5: same | E5: =VLOOKUP(C:C,'FY2526 Questions & Owners-All '!E:F,2,FALSE) -> HP/TC/XQ Plant SNP Ziwei/Jason/Matt & PSC Suz. | G5: 4 | H5: Capability | I5: CNL/CNA/CSNP Resources Qualification is a Priority to ensure business continuity especially during transitions | J5: FY2425 | K5: PSC-Yan
A6: 5 | B6: Capability | C6: Process owner defined for every work process and ensures in process/out process measures are tracked & visible (MPS,DDS,POSS, PCL & POW) | D6: 更具体的process | E6: =VLOOKUP(C:C,'FY2526 Questions & Owners-All '!E:F,2,FALSE) -> HP/TC/XQ Plant SNP Ziwei/Jason/Matt & PSC Suz. | G6: 5 | H6: Capability | I6: Process owner defined for every work process and ensures in process/out process measures are tracked & visible | J6: FY2425 | K6: PSC-Yan
A7: 6 | B7: Capability | C7: IR - Is Operations team trained on using the Issue Resolution template at least annually? Training Sessions or e-mail refreshers can be used to make sure the team enabled with the right capability and tools to communicate and solve issues effectively | D7: same | E7: =VLOOKUP(C:C,'FY2526 Questions & Owners-All '!E:F,2,FALSE) -> PSC-Cookie | G7: 6 | H7: Capability | I7: IR - Is Operations team trained on using the Issue Resolution template at least annually? Training Sessions or e-mail refreshers can be used to make sure the team enabled with the right capability and tools to communicate and solve issues effectively | J7: FY2425 | K7: PSC-Cookie
A8: 7 | B8: Capability | C8: MPS - Is MPS System Owner & Department DMS Owners trained and qualified (as per SUC at right proficiency level)? | D8: same | E8: =VLOOKUP(C:C,'FY2526 Questions & Owners-All '!E:F,2,FALSE) -> HP/TC/XQ Plant SNP Ziwei/Jason/Matt/Xiaoye | G8: 7 | H8: Capability | I8: MPS - Is MPS System Owner & Department DMS Owners trained and qualified (as per SUC at right proficiency level)? | J8: FY2425 | K8: HP/TC/XQ/LY Plant SNP Yantong/Zhelun/Lijun/Xiaoye
A9: 8 | B9: Capability | C9: POSS - All relevant triggers/roles & back up roles are defined with measurable conditions and the team executed those triggers per defined conditions and PACE model | D9: same | E9: =VLOOKUP(C:C,'FY2526 Questions & Owners-All '!E:F,2,FALSE) -> HP/TC/XQ Plant SNP Ziwei/Jason/Matt | G9: 8 | H9: Capability | I9: POSS - All relevant triggers/roles & back up roles are defined with measurable conditions and the team executed those triggers per defined conditions and PACE model | J9: FY2425 | K9: HP/TC/XQ Plant SNP Yantong/Zhelun/Lijun
A10: 9 | B10: Capability | C10: PCL - Does your RBU has an owner assigned to lead parameter center-lining work, who is trained on E2E Planning Parameter Centerline PDCA, qualified on PCL SUC, can explain the fundamentals of parameter, can explain the key concept and definition of critical parameters? | D10: same | E10: PSC-Suz. | G10: 9 | H10: Capability | I10: PCL - Does your RBU has an owner assigned to lead parameter center-lining work, who is trained on E2E Planning Parameter Centerline PDCA, qualified on PCL SUC, can explain the fundamentals of parameter, can explain the key concept and definition of critical parameters? | J10: FY2425 | K10: PSC-Yan
A11: 10 | B11: Capability | C11: POW - Is there a qualified POW facilitator in place to enable quality POW execution? & the key participants trained on POW CBA, understand the role of POW in the E2E Operating Strategy process, knows the difference between POW and Parameter Loss Analysis Workshop, and can explain the inputs and outputs of a POW? | D11: same | E11: PSC-Suz. | G11: 10 | H11: Capability | I11: POW - Is there a qualified POW facilitator in place to enable quality POW execution? & the key participants trained on POW CBA, understand the role of POW in the E2E Operating Strategy process, knows the difference between POW and Parameter Loss Analysis Workshop, and can explain the inputs and outputs of a POW? | J11: FY2425 | K11: PSC-Yan
A12: 11 | B12: Capability | C12: SCSI - Does your RBU have a SCSI "go-to person" identified (e.g. Sync Leader, Key User) and qualified per SCSI Step-Up-Card to enable and sustain RBU's SCSI capability? | D12: same | E12: =VLOOKUP(C:C,'FY2526 Questions & Owners-All '!E:F,2,FALSE) -> PSC-Suz. | G12: 11 | H12: Capability | I12: SCSI - Does your RBU have a SCSI "go-to person" identified (e.g. Sync Leader, Key User) and qualified per SCSI Step-Up-Card to enable and sustain RBU's SCSI capability? | J12: FY2425 | K12: PSC-Yan
A13: 12 | B13: Capability | C13: IWS - Are all E2E VS at their targeted measures based on current IWS Phase (SCCA/SNP WAP)? | D13: same | E13: =VLOOKUP(C:C,'FY2526 Questions & Owners-All '!E:F,2,FALSE) -> HP/TC/XQ Plant SNP Ziwei/Jason/Matt & PSC Suz. | G13: 12 | H13: Capability | I13: IWS - Are all E2E VS at their targeted measures based on current IWS Phase (SCCA/SNP WAP)? | J13: FY2425 | K13: HP/TC/XQ Plant SNP Yantong/Zhelun/Lijun/PSC-Yan
A14: 13 | B14: Processes | C14: IR - Is issue resolution handled through Decision Sheets covering key IR elements to drive resolution in a timely manner, following the Category Operating Strategy Principles? | D14: same | E14: =VLOOKUP(C:C,'FY2526 Questions & Owners-All '!E:F,2,FALSE) -> PSC-Cookie | G14: 13 | H14: Processes | I14: IR - Is issue resolution handled through Decision Sheets covering key IR elements to drive resolution in a timely manner, following the Category Operating Strategy Principles? | J14: FY2425 | K14: PSC-Cookie
A15: 14 | B15: Processes | C15: MPS - Are MPS in-process measures at target/within limits (as per PMC)? | D15: same | E15: =VLOOKUP(C:C,'FY2526 Questions & Owners-All '!E:F,2,FALSE) -> HP/TC/XQ Plant SNP Ziwei/Jason/Matt/Xiaoye | G15: 14 | H15: Processes | I15: MPS - Are MPS in-process measures at target/within limits (as per PMC)? | J15: FY2425 | K15: HP/TC/XQ/LY Plant SNP Yantong/Zhelun/Lijun/Xiaoye
A16: 15 | B16: Processes | C16: MPS - Are 100% of unadjusted MPS misses properly analyzed and root caused | D16: 有改动 | E16: =VLOOKUP(C:C,'FY2526 Questions & Owners-All '!E:F,2,FALSE) -> HP/TC/XQ Plant SNP Ziwei/Jason/Matt/Xiaoye | G16: 15 | H16: Processes | I16: MPS - Are 100% of MPS misses properly analyzed and root caused (independent if adjusted or unadjusted tracking) | J16: FY2425 | K16: HP/TC/XQ/LY Plant SNP Yantong/Zhelun/Lijun/Xiaoye
A17: 16 | B17: Processes | C17: MPS - Are MPS measures reviewed during all steps of DDS cycle (Shift Handover, Line DDS, Planning/Manufacturing DDS (D2))? | D17: 有改动，增加D2 review MPS | E17: =VLOOKUP(C:C,'FY2526 Questions & Owners-All '!E:F,2,FALSE) -> HP/TC/XQ Plant SNP Ziwei/Jason/Matt/Xiaoye | G17: 16 | H17: Processes | I17: MPS - Are MPS measures reviewed during all steps of DDS cycle (Shift Handover, Line DDS, etc.)? | J17: FY2425 | K17: HP/TC/XQ/LY Plant SNP Yantong/Zhelun/Lijun/Xiaoye
A18: 17 | B18: Processes | C18: MPS - Is MPS PDCA process in place and working as designed (focus on a formal review process with leadership and a continuous improvement action plan)? | D18: same | E18: =VLOOKUP(C:C,'FY2526 Questions & Owners-All '!E:F,2,FALSE) -> HP/TC/XQ Plant SNP Ziwei/Jason/Matt/Xiaoye | G18: 17 | H18: Processes | I18: MPS - Is MPS PDCA process in place and working as designed (focus on a formal review process with leadership and a continuous improvement action plan)? | J18: FY2425 | K18: HP/TC/XQ/LY Plant SNP Yantong/Zhelun/Lijun/Xiaoye
A19: 18 | B19: Processes | C19: MPS - Are MPS measures revised reviewed and aligned with PSC (as per PMC)? | D19: same | E19: =VLOOKUP(C:C,'FY2526 Questions & Owners-All '!E:F,2,FALSE) -> HP/TC/XQ Plant SNP Ziwei/Jason/Matt/Xiaoye | G19: 18 | H19: Processes | I19: MPS - Are MPS measures revised reviewed and aligned with PSC (as per PMC)? | J19: FY2425 | K19: HP/TC/XQ/LY Plant SNP Yantong/Zhelun/Lijun/Xiaoye
A20: 19 | B20: Processes | C20: MPS - Is SNP scorecard updated with all MPS measures & correct targets as per IWS Phase and reviewed at least on quarterly basis? | D20: same | E20: =VLOOKUP(C:C,'FY2526 Questions & Owners-All '!E:F,2,FALSE) -> HP/TC/XQ Plant SNP Ziwei/Jason/Matt/Xiaoye | G20: 19 | H20: Processes | I20: MPS - Is SNP scorecard updated with all MPS measures & correct targets as per IWS Phase and reviewed at least on quarterly basis? | J20: FY2425 | K20: HP/TC/XQ Plant SNP Yantong/Zhelun/Lijun
A21: 20 | B21: Processes | C21: DDS - Are the action plans updated prior the DDS (follow-ups from previous meeting + new known issues added + Actions are updated)? If no current actions because of no issues, check action plan history to confirm action planning is done. This is applicable to D1,D2,D3,D5 & D7 | D21: 有改动， 更具体哪些DDS apply | E21: HP/TC/XQ Plant SNP Ziwei/Jason/Matt/Xiaoye for D2, PSC Initial/Cookie/Suz. for D1/D3/D5/D7 | G21: 20 | H21: Processes | I21: DDS - Are the action plans updated prior the DDS (follow-ups from previous meeting + new known issues added + Actions are updated)? If no current actions because of no issues, check action plan history to confirm action planning is done. | J21: FY2425 | K21: HP/TC/XQ/LY Plant SNP Yantong/Zhelun/Lijun/Xiaoye for D2, PSC Initial/Cookie/Yan for D1/D3/D5/D7
A22: 21 | B22: Processes | C22: DDS - Are ALL off-track measures being action planned during the DDS? | D22: same | E22: =VLOOKUP(C:C,'FY2526 Questions & Owners-All '!E:F,2,FALSE) -> HP/TC/XQ Plant SNP Ziwei/Jason/Matt/Xiaoye for D2, PSC Initial/Cookie/Suz. for D1/D3/D5/D7 | G22: 21 | H22: Processes | I22: DDS - Are ALL off-track measures being action planned during the DDS? | J22: FY2425 | K22: HP/TC/XQ/LY Plant SNP Yantong/Zhelun/Lijun/Xiaoye for D2, PSC Initial/Cookie/Yan for D1/D3/D5/D7
A23: 22 | B23: Processes | C23: DDS - Are the mandatory attendees - as per the CBA - the only participants of the meeting? | D23: same | E23: =VLOOKUP(C:C,'FY2526 Questions & Owners-All '!E:F,2,FALSE) -> HP/TC/XQ Plant SNP Ziwei/Jason/Matt/Xiaoye for D2, PSC Initial/Cookie/Suz. for D1/D3/D5/D7 | G23: 22 | H23: Processes | I23: DDS - Are the mandatory attendees - as per the CBA - the only participants of the meeting? | J23: FY2425 | K23: HP/TC/XQ/LY Plant SNP Yantong/Zhelun/Lijun/Xiaoye for D2, PSC Initial/Cookie/Yan for D1/D3/D5/D7
A24: 23 | B24: Processes | C24: DDS - Preparation - Are the latest measures actuals completed in the review tool before the meeting? | D24: same | E24: =VLOOKUP(C:C,'FY2526 Questions & Owners-All '!E:F,2,FALSE) -> HP/TC/XQ Plant SNP Ziwei/Jason/Matt/Xiaoye for D2, PSC Initial/Cookie/Suz. for D1/D3/D5/D7 | G24: 23 | H24: Processes | I24: DDS - Preparation - Are the latest measures actuals completed in the review tool before the meeting? | J24: FY2425 | K24: HP/TC/XQ/LY Plant SNP Yantong/Zhelun/Lijun/Xiaoye for D2, PSC Initial/Cookie/Yan for D1/D3/D5/D7
A25: 24 | B25: Processes | C25: DDS - Are the Targets & Escalation Triggers documented and known by respective measure owners? Are targets shown in the review tool next to the actual results? | D25: same | E25: =VLOOKUP(C:C,'FY2526 Questions & Owners-All '!E:F,2,FALSE) -> HP/TC/XQ Plant SNP Ziwei/Jason/Matt/Xiaoye for D2, PSC Initial/Cookie/Suz. for D1/D3/D5/D7 | G25: 24 | H25: Processes | I25: DDS - Are the Targets & Escalation Triggers documented and known by respective measure owners? Are targets shown in the review tool next to the actual results? | J25: FY2425 | K25: HP/TC/XQ/LY Plant SNP Yantong/Zhelun/Lijun/Xiaoye for D2, PSC Initial/Cookie/Yan for D1/D3/D5/D7
A26: 25 | B26: Processes | C26: DDS - Does the DDS review ALL and ONLY the standard measures as per the CBA? | D26: same | E26: =VLOOKUP(C:C,'FY2526 Questions & Owners-All '!E:F,2,FALSE) -> HP/TC/XQ Plant SNP Ziwei/Jason/Matt/Xiaoye for D2, PSC Initial/Cookie/Suz. for D1/D3/D5/D7 | G26: 25 | H26: Processes | I26: DDS - Does the DDS review ALL and ONLY the standard measures as per the CBA? | J26: FY2425 | K26: HP/TC/XQ/LY Plant SNP Yantong/Zhelun/Lijun/Xiaoye for D2, PSC Initial/Cookie/Yan for D1/D3/D5/D7
A27: 26 | B27: Processes | C27: DDS - Is the DDS frequency as per the CBA [Daily/Weekly/Monthly/Quarterly]? | D27: same | E27: =VLOOKUP(C:C,'FY2526 Questions & Owners-All '!E:F,2,FALSE) -> HP/TC/XQ Plant SNP Ziwei/Jason/Matt/Xiaoye for D2, PSC Initial/Cookie/Suz. for D1/D3/D5/D7 | G27: 26 | H27: Processes | I27: DDS - Is the DDS frequency as per the CBA [Daily/Weekly/Monthly/Quarterly]? | J27: FY2425 | K27: HP/TC/XQ/LY Plant SNP Yantong/Zhelun/Lijun/Xiaoye for D2, PSC Initial/Cookie/Yan for D1/D3/D5/D7
A28: 27 | B28: Processes | C28: DDS - Is the DDS taking proper time - No Gap No Yap? | D28: same | E28: =VLOOKUP(C:C,'FY2526 Questions & Owners-All '!E:F,2,FALSE) -> HP/TC/XQ Plant SNP Ziwei/Jason/Matt/Xiaoye for D2, PSC Initial/Cookie/Suz. for D1/D3/D5/D7 | G28: 27 | H28: Processes | I28: DDS - Is the DDS taking proper time - No Gap No Yap? | J28: FY2425 | K28: HP/TC/XQ/LY Plant SNP Yantong/Zhelun/Lijun/Xiaoye for D2, PSC Initial/Cookie/Yan for D1/D3/D5/D7
A29: 28 | B29: Processes | C29: POSS - Is POSS available in ePOSS? | D29: same | E29: =VLOOKUP(C:C,'FY2526 Questions & Owners-All '!E:F,2,FALSE) -> HP/TC/XQ Plant SNP Ziwei/Jason/Matt | G29: 28 | H29: Processes | I29: POSS - Is POSS available in ePOSS? | J29: FY2425 | K29: HP/TC/XQ Plant SNP Yantong/Zhelun/Lijun
A30: 29 | B30: Processes | C30: POSS - POSS is built in line with Site CBN, PSC and BU CBN, OGSM & GTM Ops strategies. Strategies are differentiated via Segmentation and Replenishment Stream (when applicable). Link to E2E Ops strategy available. Site Finance Leader was involved and verified that POSS supports Firm targets delivery. | D30: same | E30: HP/TC/XQ Plant SNP Ziwei/Jason/Matt | G30: 29 | H30: Processes | I30: POSS - POSS is built in line with Site CBN, PSC and BU CBN, OGSM & GTM Ops strategies. Strategies are differentiated via Segmentation and Replenishment Stream (when applicable). Link to E2E Ops strategy available. Site Finance Leader was involved and verified that POSS supports Firm targets delivery. | J30: FY2425 | K30: HP/TC/XQ Plant SNP Yantong/Zhelun/Lijun
A31: 30 | B31: Processes | C31: POSS - POSS alignment from BU SNO Senior Director happened within the last 12 month at min. | D31: same | E31: =VLOOKUP(C:C,'FY2526 Questions & Owners-All '!E:F,2,FALSE) -> HP/TC/XQ Plant SNP Ziwei/Jason/Matt | G31: 30 | H31: Processes | I31: POSS - POSS alignment from BU SNO Senior Director happened within the last 12 month at min. | J31: FY2425 | K31: HP/TC/XQ Plant SNP Yantong/Zhelun/Lijun
B32: Processes | C32: POSS - POSS is known and used by both plant and BU organizations (PSC). (Random check of parameters aligned with plant SPOCs and PSC Planners) | D32: 删除 | E32: - | G32: 31 | H32: Processes | I32: POSS - POSS is known and used by both plant and BU organizations (PSC). (Random check of parameters aligned with plant SPOCs and PSC Planners) | J32: FY2425 | K32: HP/TC/XQ Plant SNP Yantong/Zhelun/Lijun
A33: 31 | B33: Processes | C33: POSS - POSS deviations are monitored in the Mfg. Daily DDS (D2), and gap analysis on those deviations are reviewed in Weekly DDS (D6) Scheduling and Results review and PDCA is in place to reduce the number of POSS deviations. | D33: same | E33: =VLOOKUP(C:C,'FY2526 Questions & Owners-All '!E:F,2,FALSE) -> HP/TC/XQ Plant SNP Ziwei/Jason/Matt | G33: 32 | H33: Processes | I33: POSS - POSS deviations are monitored in the Mfg. Daily DDS (D2), and gap analysis on those deviations are reviewed in Weekly DDS (D6) Scheduling and Results review and PDCA is in place to reduce the number of POSS deviations. | J33: FY2425 | K33: HP/TC/XQ Plant SNP Yantong/Zhelun/Lijun
A34: 32 | B34: Processes | C34: PCL - Are the compliance results of your parameter governance measures reviewed monthly, gap analyzed with action plan identified? | D34: same | E34: =VLOOKUP(C:C,'FY2526 Questions & Owners-All '!E:F,2,FALSE) -> PSC-Suz. | G34: 33 | H34: Processes | I34: PCL - Are the compliance results of your parameter governance measures reviewed monthly, gap analyzed with action plan identified? | J34: FY2425 | K34: PSC-Yan
B35: Processes | C35: PCL - Is the monthly/weekly pit-stop and daily DDS in place for both RPI and FP parameter centerline improvement, reflecting the demonstrated capability? | D35: 删除 | E35: - | G35: 34 | H35: Processes | I35: PCL - Is the monthly/weekly pit-stop and daily DDS in place for both RPI and FP parameter centerline improvement, reflecting the demonstrated capability? | J35: FY2425 | K35: PSC-Yan
B36: Processes | C36: PCL - Is your category leveraging standard parameter center-lining tools to drive parameter center-lining (e.g. MD&CL, IP@100, etc.) | D36: 删除 | E36: - | G36: 35 | H36: Processes | I36: PCL - Is your category leveraging standard parameter center-lining tools to drive parameter center-lining (e.g. MD&CL, IP@100, etc.) | J36: FY2425 | K36: PSC-Yan
B37: Processes | C37: POW Are your RBU SNO leader and GTM Director enrolled in the E2E Operating Strategy process, and understand the role of POW in the process include its purpose and value? | D37: 删除 | E37: - | G37: 36 | H37: Processes | I37: POW Are your RBU SNO leader and GTM Director enrolled in the E2E Operating Strategy process, and understand the role of POW in the process include its purpose and value? | J37: FY2425 | K37: PSC-Yan
A38: 33 | B38: Processes | C38: POW - Does your RBU have a Category Operating Strategy Choices (Step 9 in the E2E Operating Strategy process) in place with right level of granularity (e.g. by replenishment stream by segment choices are clear), which is renewed annually according to the Business Strategy? | D38: same | E38: PSC-Suz. | G38: 37 | H38: Processes | I38: POW - Does your RBU have a Category Operating Strategy Choices (Step 9 in the E2E Operating Strategy process) in place with right level of granularity (e.g. by replenishment stream by segment choices are clear), which is renewed annually according to the Business Strategy? | J38: FY2425 | K38: PSC-Yan
A39: 34 | B39: Processes | C39: POW - Has there been a POW completed in the last 12 months (minimum) that follows the POW CBA, with the focus on the changes in the Category Operating Strategy Choices (rather than full parameter landscape loss analysis)? | D39: same | E39: =VLOOKUP(C:C,'FY2526 Questions & Owners-All '!E:F,2,FALSE) -> PSC-Suz. | G39: 38 | H39: Processes | I39: POW - Has there been a POW completed in the last 12 months (minimum) that follows the POW CBA, with the focus on the changes in the Category Operating Strategy Choices (rather than full parameter landscape loss analysis)? | J39: FY2425 | K39: PSC-Yan
A40: 35 | B40: Processes | C40: POW - As an outcome from the POW, does your RBU have an agreed & updated (captured in the planning systems (SAP, OMP+)) set of Parameters(*) for use by the PSC and Plant which feed into the respective POSS (Plant), MOA (Market) and MOS (Materials) agreement documents for setting up in the planning systems? * prioritize the critical 10 parameters | D40: same | E40: PSC-Suz. | G40: 39 | H40: Processes | I40: POW - As an outcome from the POW, does your RBU have an agreed & updated (captured in the planning systems (SAP, OMP+)) set of Parameters(*) for use by the PSC and Plant which feed into the respective POSS (Plant), MOA (Market) and MOS (Materials) agreement documents for setting up in the planning systems? * prioritize the critical 10 parameters | J40: FY2425 | K40: PSC-Yan
B41: Processes | C41: POW - Has your operating strategy (POSS, MOA, MOS/SLEA) been updated according to POW alignment to reflect your updated supply chain capabilities? | D41: 删除 | E41: - | G41: 40 | H41: Processes | I41: POW - Has your operating strategy (POSS, MOA, MOS/SLEA) been updated according to POW alignment to reflect your updated supply chain capabilities? | J41: FY2425 | K41: PSC-Yan
A42: 36 | B42: Processes | C42: POW - As an outcome from the POW, have your RBU aligned on the critical 'governance measures' that will be reviewed monthly, where gaps will be analyzed with action plans identified? | D42: same | E42: =VLOOKUP(C:C,'FY2526 Questions & Owners-All '!E:F,2,FALSE) -> PSC-Suz. | G42: 41 | H42: Processes | I42: POW - As an outcome from the POW, have your RBU aligned on the critical 'governance measures' that will be reviewed monthly, where gaps will be analyzed with action plans identified? | J42: FY2425 | K42: PSC-Yan
A43: 37 | B43: Processes | C43: SCSI - Are DBNx measures being reported on a monthly basis and reviewed with LT when gaps are found with action plans identified? | D43: same | E43: =VLOOKUP(C:C,'FY2526 Questions & Owners-All '!E:F,2,FALSE) -> HP/TC/XQ Plant SNP Ziwei/Jason/Matt | G43: 42 | H43: Processes | I43: SCSI - Are DBNx measures being reported on a monthly basis and reviewed with LT when gaps are found with action plans identified? | J43: FY2425 | K43: HP/TC/XQ Plant SNP Yantong/Zhelun/Lijun
A44: 38 | B44: Processes | C44: SCSI - Has your RBU identified agility / SC resilience targets (DBNx target and SCT target) per appropriate supply chain segment (value stream, market, material type, etc.)? | D44: same | E44: =VLOOKUP(C:C,'FY2526 Questions & Owners-All '!E:F,2,FALSE) -> PSC-Suz. | G44: 43 | H44: Processes | I44: SCSI - Has your RBU identified agility / SC resilience targets (DBNx target and SCT target) per appropriate supply chain segment (value stream, market, material type, etc.)? | J44: FY2425 | K44: PSC-Yan
A45: 39 | B45: Processes | C45: SCSI - Is SCSI used to identify losses as part of the annual RBU Inventory Loss analysis and/or the annual Plant Mfg. Sync/Agility workshops? | D45: same | E45: =VLOOKUP(C:C,'FY2526 Questions & Owners-All '!E:F,2,FALSE) -> PSC-Suz. | G45: 44 | H45: Processes | I45: SCSI - Is SCSI used to identify losses as part of the annual RBU Inventory Loss analysis and/or the annual Plant Mfg. Sync/Agility workshops? | J45: FY2425 | K45: PSC-Yan
A46: 40 | B46: Processes | C46: Manu. Agility Workshop - is RBU checking Manufacturing Agility opportunities at least once per plant in the last 12 months & conducting agility workshops (MSAnT, QPQ, OSSM…etc.) accordingly as per BU alignment? | D46: 有改动，MSAnT 换成Manu. Agility Workshop | E46: =VLOOKUP(C:C,'FY2526 Questions & Owners-All '!E:F,2,FALSE) -> HP/TC/XQ Plant SNP Ziwei/Jason/Matt | G46: 45 | H46: Processes | I46: MSAnT - is RBU checking Manufacturing Agility opportunities at least once per plant in the last 12 months & conducting MSAnT workshops accordingly as per BU alignment? | J46: FY2425 | K46: HP/TC/XQ Plant SNP Yantong/Zhelun/Lijun
A47: 41 | B47: Processes | C47: Manu. Agility Workshop - Is your Manufacturing Agility Implementation plan up to date & results tracked at least quarterly (preferrably monthly)? | D47: 有改动，MSAnT 换成Manu. Agility Workshop | E47: =VLOOKUP(C:C,'FY2526 Questions & Owners-All '!E:F,2,FALSE) -> HP/TC/XQ Plant SNP Ziwei/Jason/Matt | G47: 46 | H47: Processes | I47: MSAnT - Is your Manufacturing Agility Implementation plan up to date & results tracked at least quarterly (preferably monthly)? | J47: FY2425 | K47: HP/TC/XQ Plant SNP Yantong/Zhelun/Lijun
A48: 42 | B48: Processes | C48: Manu. Agility workshop - Have your updated parameters been captured in POSS & SAP as outcome of MSAnT? | D48: 有改动，MSAnT 换成Manu. Agility Workshop | E48: =VLOOKUP(C:C,'FY2526 Questions & Owners-All '!E:F,2,FALSE) -> HP/TC/XQ Plant SNP Ziwei/Jason/Matt | G48: 47 | H48: Processes | I48: MSAnT - Have your updated parameters been captured in POSS & SAP as outcome of MSAnT? | J48: FY2425 | K48: HP/TC/XQ Plant SNP Yantong/Zhelun/Lijun
B49: Processes | C49: MSAnT - Has your DDS process been enhanced to include Manufacturing Synchronization RTT and defects being closed on time? | D49: 删除 | E49: - | G49: 48 | H49: Processes | I49: MSAnT - Has your DDS process been enhanced to include Manufacturing Synchronization RTT and defects being closed on time? | J49: FY2425 | K49: HP/TC/XQ Plant SNP Yantong/Zhelun/Lijun
A50: 43 | B50: Processes | C50: IWS - SNP WAP has been done in the last 12 months & action plan shared with PSC (For IWS phases 1-4) or all E2E VS Assessment has been done in the last 12 months (For IWS5.0 phases)? | D50: same | E50: =VLOOKUP(C:C,'FY2526 Questions & Owners-All '!E:F,2,FALSE) -> HP/TC/XQ Plant SNP Ziwei/Jason/Matt | G50: 49 | H50: Processes | I50: IWS - SNP WAP has been done in the last 12 months & action plan shared with PSC (For IWS phases 1-4) or all E2E VS Assessment has been done in the last 12 months (For IWS5.0 phases)? | J50: FY2425 | K50: HP/TC/XQ Plant SNP Yantong/Zhelun/Lijun
A51: 44 | B51: Systems | C51: IR - Is there a central documentation gathering decision sheets for different issues to enable learning and reapplication and reduce repetition of similar issues | D51: same | E51: =VLOOKUP(C:C,'FY2526 Questions & Owners-All '!E:F,2,FALSE) -> PSC-Cookie | G51: 50 | H51: Systems | I51: IR - Is there a central documentation gathering decision sheets for different issues to enable learning and reapplication and reduce repetition of similar issues | J51: FY2425 | K51: PSC-Cookie
A52: 45 | B52: Systems | C52: MPS - Is master data updated by System Owner & following MPS standard? | D52: same | E52: =VLOOKUP(C:C,'FY2526 Questions & Owners-All '!E:F,2,FALSE) -> HP/TC/XQ Plant SNP Ziwei/Jason/Matt/Xiaoye | G52: 51 | H52: Systems | I52: MPS - Is master data updated by System Owner & following MPS standard? | J52: FY2425 | K52: HP/TC/XQ/LY Plant SNP Yantong/Zhelun/Lijun/Xiaoye
A53: 46 | B53: Systems | C53: DDS - Are the measures reviewed & action planning done using the standard tool? [DDS-i OR a locally developed dashboard, only if aligned with respective HPN RPL for the region] | D53: same | E53: =VLOOKUP(C:C,'FY2526 Questions & Owners-All '!E:F,2,FALSE) -> HP/TC/XQ Plant SNP Ziwei/Jason/Matt/Xiaoye for D2, PSC Initial/Cookie/Suz. for D1/D3/D5/D7 | G53: 52 | H53: Systems | I53: DDS - Are the measures reviewed & action planning done using the standard tool? [DDS-i OR a locally developed dashboard, only if aligned with respective HPN RPL for the region] | J53: FY2425 | K53: HP/TC/XQ/LY Plant SNP Yantong/Zhelun/Lijun/Xiaoye for D2, PSC Initial/Cookie/Yan for D1/D3/D5/D7
A54: 47 | B54: Systems | C54: PCL- Is the E2E Parameter Centerline tool leveraged to support the execution of operating strategy execution, include planning orchestration workshop preparation, execution, and ongoing governance to enable identification of losses/opportunities? | D54: same | E54: =VLOOKUP(C:C,'FY2526 Questions & Owners-All '!E:F,2,FALSE) -> PSC-Suz. | G54: 53 | H54: Systems | I54: Is the E2E Parameter Centerline tool leveraged to support the execution of operating strategy execution, include planning orchestration workshop preparation, execution, and ongoing governance to enable identification of losses/opportunities? | J54: FY2425 | K54: PSC-Yan

Sheet Data Hub
B1: SCORE grading | D1: WP Sections | F1: LDR Sections | H1: Boolean List
B2: 0 | D2: Results | F2: Results | H2: TRUE
B3: 1 | D3: Capability | F3: Culture | H3: FALSE
B4: 2 | D4: Processes | F4: People
B5: n/a | D5: Systems | F5: Key Projects

Sheet Work Process Assessmen 1t
B1: Capacity Planning Work Process Assessment
B3: HPN: SIP | G3: =(SUM(G11:G29)/26) -> 0 | I3: Capacity Planning Adherence (total score)
B5: Owner: Mya Darli | G5: =SUM(G11:G12)/4 -> 0 | I5: Section 1 - Results
G6: =SUM(G15:G16)/4 -> 0 | I6: Section 2 - Capability
B7: Date: Jan'23 | G7: =SUM(G19:G26)/16 -> 0 | I7: Section 3 - Processes
G8: =SUM(G29:G29)/2 -> 0 | I8: Section 4 - Systems
B10: Section 1 - Results | G10: Score | I10: 0-Score Criteria | J10: 1-Score Criteria | K10: 2-Score Criteria | M10: Additional Guidance link
A11: 1 | B11: Long Term Capacity Planning : Is Capacity load % across next 18 months within operating stategy tolerance ? Note : Results can be displayed via Planning Performance Measure (via ZC574/CM01) in SAP .
A12: 2 | B12: Short Term Capacity Planning : Is Capacity load % across next 13 weeks within operating stategy tolerance ? Note : Results can be displayed via Planning Performance Measure (via ZC574/CM01) in SAP
B14: Section 2 - Capability | G14: Score | I14: 0-Score Criteria | J14: 1-Score Criteria | K14: 2-Score Criteria | M14: Additional Guidance link
A15: 3 | B15: Has the SIP Planner been trained in the initial SIP training Class?
A16: 4 | B16: All SIP functions (based on role skill map) have completed all stages of SIP Basic Step Up Card, and the SIP planner at least qualified as IRQ to independently execute the process?
B18: Section 3 - Processes | G18: Score | I18: 0-Score Criteria | J18: 1-Score Criteria | K18: 2-Score Criteria | M18: Additional Guidance link
A19: 5 | B19: Did the master data impacting capacity planning (e.g.intervals, recipe rates/setup, quota, time-phased rates, efficiency rate keys, time-phased safeties) get updated correctly as pre-requisite ? If using OMP , OMP Master data such as GDMProcess : PV Preference,PV cost , GDMMachine: MinNetUsage,MaxNetUsage, SeqDepStepSetup : Setup time should also be checked and updated accordingly .
A20: 6 | B20: Was weekly demand verification process done by CSP to ensure valid demand plan get passed ?
A21: 7 | B21: Did any temporary firm orders get unfirmed in SAP prior to evaluating capacity ? If using OMP , was fixed planned cells outside locked zone get unfixed and set plan to zero before running PG standard solver ? (optional)
A22: 8 | B22: If using OMP , was planned cells fixed according to new exceptions ( e.g. EO , any other constraints etc.) before running PG standard solver ? (optional) N/A if business is using SAP for capacity planning
A23: 9 | B23: If using SAP, did auto-leveling get reset and MRP batch job run prior to evaluating capacity? N/A if business is using OMP for capacity planning.
A24: 10 | B24: If using SAP ,is operating strategy to balance capacity (e.g. prebuild periods, resources to offload) clear and does planner know which selection in auto leveling process can be adjusted ? If using OMP , is operating strategy to balance capacity clear and does planner know different types of basic solvers available to further balance ?
A25: 11 | B25: Did each resource get balanced to within the tolerances, and according to the operating strategy, documented in POSS?
A26: 12 | B26: Did the balanced plan, or any capacity gaps, get communicated to the CSP Planner after balancing was completed?
B28: Section 4 - Systems | G28: Score | I28: 0-Score Criteria | J28: 1-Score Criteria | K28: 2-Score Criteria | M28: Additional Guidance link
A29: 13 | B29: Is the SAP Autoleveling or OMP the only system for capacity planning process ? No other (ex. Excel files) solutions are in place?

Sheet Maintenance Chart
E1: CAPACITY PLANNING
B3: PILLAR: Site Integrated Planning HPN | F3: Review Date: 03.03.2022 | H3: Version: 0.1
B4: 1. System Owner: Site Integrated Planner 1.1 Process SIP BPX Owner: Mya Darli | F4: 2. Process Name: Capacity Planning | H4: 3. Products of the System: The resulting plan is balanced across the entire planning horizon such that the business possesses sufficient capacity to deliver the plan in line with the parameters of the site and category operating strategies. This analysis identifies shortages in capacity and supports development of contingency plans where and when appropriate.
B5: 4. Business Customer/Requirements: ensure production is planned in the most efficient, lowest cost manner with the intent of delivering customer service while maximizing cash efficiency. Balancing capacity across the planning horizon enables all other organizations to develop executable plans. | F5: 5. Customers: - CSNP - MSM - Initiative Delivery Teams - Business Leader | H5: 6. Customer Requirements: - Short term balanced plan at least weekly - Long term balanced plan at least monthly in line with the BOP schedule - Capacity issues identified and resolved with sufficient lead time to deliver business objectives - Communication of capacity position to all appropriate customers (ex: C:D compliance)
B6: 7. Process Measures: CASH – Inventory builds due to lack of capacity COST – Site costs due to under-utilized resources and Overtime/expediting costs due to capacity shortages CFR – Service issues due to lack of capacity | F6: 8. Results Tracking: Intervals Maintenance Executed (in Resource PMC) Recipe Rate Analysis executed (in Recipe PMC) Monthly Capacity Load Balanced for LTP no greater than operating strategy tolerance Weekly Capacity Load Balanced for STP no greater than operating strategy tolerance
B7: 9. Process Flow Chart | F7: 10. Process Maintenance Chart
F8: Measures | G8: Who Monitors? | H8: Monitoring Frequency | I8: Control or Action Limits | J8: Who Investigates?
F9: Output Measures | H9: Process Monitoring
F10: CFR | G10: CSNP | H10: Monthly | J10: SIP
F11: Cash | G11: CSNP | H11: Monthly | J11: SIP
F12: Cost | G12: F&A | H12: Monthly | J12: SIP
F13: In-Process Measures | H13: Process Monitoring
F14: Supply Parameter Update Intervals Update | G14: SIP Planner | H14: Weekly | I14: Yes | J14: SIP Planner
F15: Supply Parameter Update Rates Updated | G15: SIP Planner | H15: Quarterly | I15: Yes | J15: SIP Planner
F16: Final Evaluation: Monthly Capacity Load Balanced | G16: SIP Planner | H16: Weekly | I16: 1 | J16: SIP Planner
F17: Final Evaluation: Monthly Capacity Load Balanced | G17: SIP Planner | H17: Monthly | I17: 1 | J17: SIP Planner
F19: Process Control Measures | H19: Process Monitoring
F20: Capacity Planning Health Check score | G20: SIP Ops Leader | H20: Yearly | I20: executed | J20: SIP Ops Leader

Sheet Flowchart
E1: CAPACITY PLANNING

Sheet Terminology
C1: CAPACITY PLANNING
B2: Term | C2: Description
B3: Planning Time Fence (PTF) | C3: Time frame in which you plan to have some control over the changes made to your production schedule
B4: Recipe | C4: Define how a finished product is made. In SAP it is the set of instructions for making a product. There may be alternate instructions for making the same product so there may be multiple recipes for one material
B5: Finite Schedule | C5: This is a planning system for manufacturing that is planned within the capacity limits of work centers
B6: Capacity Evaluation | C6: Comparison of required capacity to available capacity
B7: Material Requirement Planning (MRP) | C7: Programs that calculate the requirements and procurement plans for nonmaster scheduled materials
B8: Lot Size | C8: The specified quantity of an order that is to be delivered at a particular point in time.
B9: Quota | C9: Determine which Production Version will be used for each Planned Order created by SAP. Also allow for flexible control of time-phased periods and quantities from one or more other Plants, and are used by Purchasing to split purchases across more than one Vendor

Sheet Measures Definition & Scorecard
C1: CAPACITY PLANNING
B2: MEASURE | C2: DEFINITION
B3: Monthly Capacity Load Balanced for LTP no greater than operating strategy tolerance | C3: Monthly capacity load in CM01/ZC574 for next 18 months for each resource/plant combination is not greater than the tolerance defined in POSS in attachment "Autoleveling Strategy" (max. Load level for capacity field e.g.: 100% or 95%).
B4: Weekly Capacity Load Balanced for STP no greater than operating strategy tolerance | C4: STP capacity load in CM01/ZC574 for next 13 weeks for each resource/plant combination is is not greater than the tolerance defined in POSS in attachment "Autoleveling Strategy" (max. Load level for capacity field e.g.: 100% or 95%) and is the result is reviewed in weekly VS Planning DDS and documented in meeting notes
B5: Intervals Maintenance weekly for STP and Monthly for LTP | C5: Intervals should be updated weekly for next 13 weeks and monthly for next 18 months to reflect the real uptime of resources, the source of this information is the output of Weekly Scheduling and Results Review DDS were requests of PE uploaded in SharePoint are discussed
B6: Recipe Rate Analysis Report monthly | C6: This report should be run monthly to audit the rate stated in recipes and the actual rate of process orders based on date/time they were started and finished by PE
B8: Scorecard for Process / DMS Owner to Execute
C9: CAPACITY PLANNING
B10: Measures | C10: Defined Target / Control Limit | D10: Jul'23 | E10: Aug'23 | F10: Sep'23 | G10: Oct'23 | H10: Nov'23 | I10: Dec'23 | J10: Jan'24 | K10: Feb'24 | L10: Mar'24 | M10: Apr'24 | N10: May'24 | O10: Jun'24
B11: In process Measure 1 | C11: xxx
B12: In process Measure 2 | C12: xxx
B13: In process Measure xx | C13: xxx
B14: Output Measure 1 | C14: xxx
B15: Output Measure 2 | C15: xxx
